Workbook
Name valuevx: 42.314159

Sheet Perhitungan
A1: KYD | B1: 177239440000 | D1: Rencana | E1: =198299502.86124*1000 -> 1.982995e+11
A2: DPK | B2: =+B4+B5+B3 -> 88657499000 | D2: Rencana | E2: =+E4+E5+E3 -> 9.49522e+10
A3: Giro | B3: 4895686000 | E3: =1473602.42120394*1000 -> 1.4736024e+09
A4: Tabungan | B4: 62330813000 | E4: =75474929.7402169*1000 -> 7.547493e+10
A5: Deposito | B5: 21431000000 | E5: =18003668.1343618*1000 -> 1.8003668e+10
A6: CKPN | B6: 7056793000
A7: Adanya Fraud | D7: Kekurangan Personil | E7: 0
A8: Surat Pengaduan Nasabah
A9: Frekuensi Temuan
A10: Sekarang | B10: 72
A11: Sebelumnya | B11: 61
A12: Tindak Lanjut Temuan | B12: 0.993
A14: Kredit sandi 1 | B14: 165892940000 | D14: Realisasi | E14: 263
A15: Kredit sandi 2 | B15: 3919425000 | D15: Menunggak | E15: 1
A16: Kredit sandi 3 | B16: 98341000
A17: Kredit sandi 4 | B17: 17128000
A18: Kredit sandi 5 | B18: 7311607000
A19: Total Kredit | B19: =SUM(B14:B18) -> 177239441000
C21: Total Aset | D21: Total Aktiva Produktif | E21: Laba sblm pajak
B22: 1
B23: 2
B24: 3
B25: 4
B26: 5
B27: 6
B28: 7
B29: 8
B30: 9 | C30: 176317766000 | D30: 170182647000 | E30: 4543119000
A31: Total | C31: =SUM(C22:C30) -> 176317766000 | D31: =SUM(D22:D30) -> 170182647000 | E31: =SUM(E22:E30) -> 4543119000
A32: Disetahunkan | C32: =C31/9*12 -> 2.3509035e+11 | D32: =D31/9*12 -> 226910196000 | E32: =E31/9*12 -> 6057492000
A33: Rata-rata | C33: =C31/1 -> 176317766000 | D33: =D31/1 -> 170182647000 | E33: =E31/1 -> 4543119000
A36: Pendapatan Bunga Bersih Disetahunkan | D36: =D37/9*12 -> 20074528000
A37: Pendapatan Bunga Bersih (Pendapatan Bunga (1) - Biaya Bunga (2)) | D37: =D38-D39 -> 15055896000
A38: 1.Pendapatan Bunga (Bunga Yang Diperoleh+Propisi dan Komisi Kredit) | D38: =D42+D43 -> 17270373000
A39: 2.Biaya Bunga (Bunga Yang Dibyr+Hadiah+Propisi dan Komisi Yang Dibyr Utk Mendptkan Dana) | D39: =D47+D48+D49 -> 2214477000
A40: 4.Pendapatan Bunga Bersih (Pendapatan Bunga - Biaya Bunga) | D40: =+D38-D39 -> 15055896000
A41: 5.Pendapatan Lain (Total Pendapatan-Bunga Yang Diperoleh-Propisi & Komisi Kredit) | D41: =+D46-D38 -> 6269855000
A42: Bunga Yang Diperoleh | D42: 17260501000
A43: Provisi & Komisi Kredit | D43: 9872000
A44: Pendapatan Operasional | D44: =+D46-D45 -> 23540228000
A45: Pendapatan Non Operasional
A46: Total Pendapatan | D46: 23540228000
A47: Bunga Yang Dibayar | D47: 2110185000
A48: Hadiah
A49: Prov.& Kom.yg dibayar utk dana | D49: 104292000
A50: Penyisihan & Penurunan Aktiva Produktif
A51: Beban Operasional | D51: =+D53-D52 -> 9093485000
A52: Beban Non Operasional | D52: 9903624000
A53: Total Biaya | D53: 18997109000
A54: Laba/(Rugi) | D54: =D46-D53 -> 4543119000
A55: Laba/(Rugi) setahun | D55: =D54/10*12 -> 5451742800

Sheet HASIL PENILAIAN
B3: Hasil Penilaian terkait Keamanan Siber Bank Sumut
C5: Nama Bank : PT Bank Sumut
C6: Tahun : 2025
B9: Penilaian Risiko Inheren terkait Keamanan Siber | F9: Penilaian Tingkat Maturitas Keamanan Siber
B10: No. | C10: Faktor Penilaian | D10: Peringkat | F10: No. | G10: Faktor Penilaian | H10: Peringkat
B11: 1 | C11: Teknologi | D11: =Teknologi!H17 -> Moderate | F11: 1 | G11: Kualitas Penerapan Manajemen Risiko terkait Keamanan Siber | H11: =KPMR!E62 -> Fair
B12: 2 | C12: Produk Bank | D12: ='Produk Bank'!H12 -> Moderate
B13: 3 | C13: Karakteristik Organisasi | D13: ='Karakter Organisasi'!H10 -> Low to Moderate | F13: 2 | G13: Kualitas Penerapan Proses Ketahanan Siber | H13: ='Kualitas Ketahanan'!D30 -> Satisfactory
B14: 4 | C14: Rekam Jejak Insiden Siber | D14: ='Rekam Jejak'!H9 -> Low
B15: Peringkat Risiko Inheren terkait Keamanan Siber | D15: ='All Inheren'!F10 -> Low to Moderate | F15: Peringkat Tingkat Maturitas Keamanan Siber | H15: =Maturitas!F10 -> Tingkat 2
B16: Analisis | F16: Analisis
B17: a. Masih menggunakan full outsource dalam Core Banking System dan Core Switching System serta memiliki beberapa host to host ke pihak ketiga. b. Banyak menggunakan interkoneksi ke Internet Publik c. Memiliki jaringan kantor yang tersebar di lebih dari 300 lokasi. d. Sudah mengimplementasikan Fraud Detection System (FDS) e. Hanya menerbitkan kartu debit dimana pengisian ATM lebih banyak dikelola oleh pihak ketiga. f. Turn over pergantian SDM yang menangani IT/ Keamanan Siber dinilai masih rendah, SDM terkait siber masih terbatas | F17: Secara umum Bank Sumut sudah memiliki pedoman dalam penerapan manajemen risiko terkait ketahanan dan kemanan siber dan terus akan dilakukan evaluasi/kaji ulang sesuai dengan keperluannya, selain itu juga telah mengimplementasikan beberapa infrastruktur seperti firewall, antispam, network VPN dan lain-lain untuk pengamanan terhadap adanya serangan (security control). Bank sudah memiliki Security Operation Center (SOC + SIEM) untuk memonitoring adanya ancaman siber yang menyerang ke sistem aplikasi Bank.
B27: Peringkat Tingkat Risiko terkait Keamanan Siber | E27: ='RATING SIBER'!F10 -> Low to Moderate
B29: Analisis
B30: Peringkat Tingkat Risiko terkait Keamanan Siber dinilai Low To Moderate, Dengan mempertimbangkan aktivitas bisnis yang dilakukan Bank, kemungkinan kerugian yang dihadapi Bank dari risiko inheren terkait keamanan siber tergolong rendah selama periode waktu tertentu pada masa depan, karena penggunaan TI yang terbatas, saat ini bank sumut belum merupakan bank digital. Sehingga kerentanan terhadap siber dinilai rendah, hal ini ditunjukkan dari risiko inheren bank dimana masih menggunakan full outsource untuk core banking dan core switching dengan kompleksitas rendah, produk bank yang disalurkan menggunakan TI masih terbatas, turn over pegawai yang menangani TI/keamanan Siber masih rendah, untuk presentase insiden siber sendiri masih berdampak hanya pada intern bank. Bank juga sudah memiliki pedoman dalam penerapan manajemen risiko terkait ketahanan dan keamanan siber serta melengkapi dengan aplikasi firewall, antispam, Security Operation Center (SOC+SIEM), dll untuk security control

Sheet Teknologi
A1: A. Kertas Kerja Penilaian Risiko Inheren terkait Keamanan Siber - Teknologi
A3: 1. Teknologi | C3: Level Risiko | H3: Hasil Penilaian | I3: Penjelasan
C4: Low (1) | D4: Low to Moderate (2) | E4: Moderate (3) | F4: Moderate to High (4) | G4: High (5)
A5: 1.1. | B5: Interkoneksi ke internet publik | C5: Kurang atau sama dengan 2 koneksi | D5: 4 koneksi | E5: 6 koneksi | F5: 8 koneksi | G5: Lebih atau sama dengan 10 koneksi | H5: 5 | I5: Aplikasi yang diakses internet public seperti Mail, Dokumen Elektronik, ePendidikan, eSTS, ePDAM, ePasar, CMS Kasda, IB Kasda,Smartloan, eCustody, SNAP, Mobile Banking, Laku Pandai, dll
A6: 1.2. | B6: Interkoneksi ke pihak ketiga (third party) | C6: Lebih dari 80% total koneksi ke pihak ketiga menggunakan Application Programming Interface (API) | D6: Hingga 50% dari total koneksi ke pihak ketiga menggunakan API | E6: Lebih dari 80% total koneksi ke pihak ketiga menggunakan host to host | F6: Hingga 50% total koneksi ke pihak ketiga menggunakan host to host | G6: Lebih dari 50% total koneksi ke pihak ketiga menggunakan direct connection | H6: 1 | I6: Koneksi ke third party seperti Pemda, Universitas, Asuransi, PDAM
A7: 1.3. | B7: Akses ke aset TI Bank | C7: Koneksi kabel hanya untuk pegawai | D7: Koneksi kabel untuk pegawai saja dan Wi-Fi untuk pihak ketiga terotorisasi | E7: Seluruh koneksi untuk pegawai dan pihak ketiga terotorisasi | F7: Seluruh koneksi untuk pegawai dan pihak ketiga terotorisasi, namun Wi-Fi untuk publik | G7: Seluruh koneksi untuk semua pihak | H7: 3 | I7: Hanya digunakan untuk kebutuhan kegiatan operasional pegawai
A8: 1.4. | B8: Jaringan intranet dari jaringan kantor Bank | C8: Bank memiliki jaringan kantor Bank yang tersebar kurang dari 100 lokasi | D8: Bank memiliki jaringan kantor Bank yang tersebar di 100 hingga 300 lokasi | E8: Bank memiliki jaringan kantor Bank yang tersebar di lebih dari 300 hingga 500 lokasi | F8: Bank memiliki jaringan kantor Bank yang tersebar di lebih dari 500 hingga 700 lokasi | G8: Bank memiliki jaringan kantor Bank yang tersebar di lebih dari 700 lokasi | H8: 3 | I8: Jaringan intranet Bank tersebar di 479 titik jaringan kantor, kas mobil, payment point, ATM & CRM, third party
A9: 1.5. | B9: Penggunaan pihak penyedia jasa TI dalam penyelenggaraan pusat data | C9: Tidak ada penggunaan jasa pihak penyedia jasa TI dalam penyelenggaraan pusat data | D9: Penggunaan jasa pihak penyedia jasa TI selain cloud service provider dalam penyelenggaraan pusat data | E9: Penggunaan jasa cloud service provider berupa SaaS | F9: Penggunaan jasa cloud service provider berupa PaaS | G9: Penggunaan jasa cloud service provider berupa IaaS | H9: 2 | I9: Bank menggunakan jasa pihak ketiga dalam penyelenggaraan pusat data secara full Managed
A10: 1.6. | B10: Pengelolaan perangkat lunak yang digunakan untuk mendukung kegiatan operasional Bank (termasuk kebutuhan back-office dan TI) | C10: Seluruh perangkat lunak yang digunakan untuk mendukung kegiatan operasional Bank (termasuk kebutuhan back office & TI) dikelola (dikembangkan dan diselenggarakan) oleh tim TI Bank | D10: Lebih dari 70% perangkat lunak yang digunakan untuk mendukung kegiatan operasional Bank (termasuk kebutuhan back office & TI) dikelola (dikembangkan dan diselenggarakan) oleh tim TI Bank | E10: Lebih dari 50% perangkat lunak yang digunakan untuk mendukung kegiatan operasional Bank (termasuk kebutuhan back-office & TI) dikelola (dikembangkan dan diselenggarakan) oleh tim TI Bank | F10: Lebih dari 30% perangkat lunak yang digunakan untuk mendukung kegiatan operasional Bank (termasuk kebutuhan back office & TI) dikelola (dikembangkan dan diselenggarakan) oleh tim TI Bank | G10: Hingga 30% perangkat lunak yang digunakan untuk mendukung kegiatan operasional Bank (termasuk kebutuhan back-office dan TI) dikelola (dikembangkan dan diselenggarakan) oleh tim TI Bank | H10: 3 | I10: Secara umum aplikasi surrounding seperti eDoc, ePendidikan, Absensi, eSTS, ePDAM, ePasar, Smartloan, dan yang lainnya dikembangkan oleh internal TI Bank.
A11: 1.7. | B11: Penggunaan perangkat keras dan/atau perangkat lunak yang sudah masuk/mendekati masa EOL | C11: Tidak ada perangkat keras dan/atau perangkat lunak yang melebihi masa EOL atau mendekati masa EOL (2 tahun ke depan akan memasuki masa EOL) | D11: Hingga 30% perangkat keras dan/atau perangkat lunak melebihi masa EOL atau mendekati masa EOL (2 tahun ke depan akan memasuki masa EOL) | E11: Hingga 50% perangkat keras dan/atau perangkat lunak melebihi masa EOL atau mendekati masa EOL (2 tahun ke depan akan memasuki masa EOL) | F11: Hingga 70% perangkat keras dan/atau perangkat lunak melebihi masa EOL atau mendekati masa EOL (2 tahun ke depan akan memasuki masa EOL) | G11: Lebih dari 70% perangkat keras dan/atau perangkat lunak melebihi masa EOL atau mendekati masa EOL (2 tahun ke depan akan memasuki masa EOL) | H11: 3 | I11: Perangkat keras PC dan perangkat lunak Operating System
A12: 1.8. | B12: Jumlah pegawai yang memiliki akses koneksi perangkat pribadi ke jaringan Bank (Bring Your Own Device) | C12: Tidak terdapat akses koneksi perangkat pribadi ke jaringan Bank | D12: Akses koneksi perangkat pribadi ke jaringan Bank dimiliki oleh kurang dari 5% pegawai | E12: Akses koneksi perangkat pribadi ke jaringan Bank dimiliki oleh kurang dari 10% pegawai | F12: Akses koneksi perangkat pribadi ke jaringan Bank dimiliki oleh kurang dari 25% pegawai | G12: Akses koneksi perangkat pribadi ke jaringan Bank dimiliki oleh 25% pegawai atau lebih | H12: 2 | I12: Terdapat sejumlah perangkat pribadi yang digunakan oleh pegawai, namun penggunaan perangkat pribadi hanya dibenarkan apabila perangkat yang digunakan telah diassess dan dikonfigurasi oleh tim IT sesuai dengan ketentuan yang berlaku
A13: 1.9. | B13: Perangkat lunak yang dapat diakses menggunakan perangkat pribadi ke jaringan Bank | C13: Tidak terdapat perangkat lunak yang dapat diakses menggunakan perangkat pribadi | D13: Perangkat pribadi yang terhubung ke jaringan Bank hanya dapat mengakses surat elektronik | E13: Perangkat pribadi yang terhubung ke jaringan Bank hanya dapat mengakses surat elektronik dan aplikasi penunjang (tidak bersifat kritikal) | F13: Perangkat pribadi yang terhubung ke jaringan Bank dapat mengakses aplikasi kritikal | G13: Perangkat pribadi yang terhubung ke jaringan Bank dapat mengakses seluruh sistem/aplikasi (termasuk core banking system) | H13: 3 | I13: Terdapat sejumlah perangkat pribadi yang digunakan oleh pegawai, namun penggunaan perangkat pribadi hanya dibenarkan apabila perangkat yang digunakan telah diassess dan dikonfigurasi oleh tim IT sesuai dengan ketentuan yang berlaku. IP Destionation disesuaikan dengan kebutuhan pengguna dan terbatas
A14: 1.10. | B14: Pihak ketiga yang memiliki akses terhadap sistem internal Bank dan/atau informasi sensitif | C14: Tidak terdapat pihak ketiga atau individu dari pihak ketiga yang memiliki akses terhadap sistem internal Bank dan/atau informasi sensitif | D14: Jumlah minimal (1 – 3 entitas atau kurang dari 10 individu) memiliki akses terhadap sistem internal Bank dan/atau informasi sensitif | E14: Jumlah sedang (4 – 6 entitas atau kurang dari 20 individu) memiliki akses terhadap sistem internal Bank dan/atau informasi sensitif | F14: Jumlah signifikan (7 – 10 entitas atau kurang dari 30 individu) memiliki akses terhadap sistem internal Bank dan/atau informasi sensitif | G14: Jumlah substansial (Lebih dari 10 entitas atau 30 individu atau lebih) memiliki akses terhadap sistem internal Bank dan/atau informasi sensitif | H14: 2 | I14: Full Outsource Core Banking System, Core Switching System dan Mobile Banking System
G16: Avg | H16: =SUM(H5:H14)/10 -> 2.7
G17: Peringkat | H17: =IF(H16<=1,("Low"),IF(H16<=2,("Low to Moderate"),IF(H16<=3,("Moderate"),IF(H16<=4,("Moderate to High"),"High")))) -> Moderate

Sheet Produk Bank
A1: B. Kertas Kerja Penilaian Risiko Inheren terkait Keamanan Siber - Produk Bank
A3: 2. Produk Bank | C3: Level Risiko | H3: Hasil Penilaian | I3: Penjelasan
C4: Low (1) | D4: Low to Moderate (2) | E4: Moderate (3) | F4: Moderate to High (4) | G4: High (5)
A5: 2.1. | B5: Penggunaan saluran daring dan mobile dalam memberikan layanan | C5: Tidak ada aplikasi (baik back office maupun untuk nasabah) yang menggunakan saluran daring dan mobile | D5: Saluran daring dan mobile digunakan untuk penyampaian informasi umum Bank kepada masyarakat (antara lain notifikasi/berita, lokasi jaringan kantor, dan produk Bank yang tersedia) | E5: Saluran daring dan mobile digunakan untuk pelayanan transaksi perbankan (produk Bank) bagi nasabah badan usaha secara domestik | F5: Saluran daring dan mobile digunakan untuk pelayanan transaksi perbankan (produk Bank) bagi nasabah ritel secara domestik | G5: Saluran daring dan mobile digunakan untuk: 1. kebutuhan produk bagi nasabah badan usaha dan ritel termasuk remitansi luar negeri dan pertukaran mata uang; dan/atau 2. interkoneksi dengan ekosistem ekonomi digital (contoh: super app) | H5: 4 | I5: Layanan perbankan untuk nasabah seperti mobile banking, ATM, internet banking, Sumut Link
A6: 2.2. | B6: Mekanisme pengelolaan ATM | C6: Bank tidak memiliki layanan ATM | D6: Layanan ATM tersedia, namun Bank tidak memiliki mesin ATM sendiri | E6: Layanan ATM tersedia, mesin ATM dan proses pengisian uang dikelola sepenuhnya oleh Bank | F6: Layanan ATM tersedia, mesin ATM dan proses pengisian uang dikelola dengan kombinasi antara Bank dan pihak ketiga | G6: Layanan ATM tersedia, mesin ATM dan pengisian uang dikelola sepenuhnya oleh pihak ketiga | H6: 4 | I6: Proses pengisian ATM dikombinasikan antara internal Bank dengan Vendor
A7: 2.3. | B7: Produk Bank berupa APMK | C7: Bank tidak menerbitkan APMK | D7: Bank hanya menerbitkan APMK berupa kartu debit untuk mendukung layanan Bank tersebut | E7: Bank menerbitkan APMK (kartu debit dan APMK lainnya) hanya untuk mendukung layanan Bank tersebut | F7: Bank menerbitkan APMK untuk 1 hingga 5 bank lain/institusi keuangan lain | G7: Bank menerbitkan APMK untuk lebih dari 5 bank lain/institusi keuangan lain | H7: 3 | I7: Hanya menerbitkan kartu debit dan e Money yang bekerja sama dengan pihak ketiga
A8: 2.4. | B8: Jenis produk Bank berbasis TI | C8: Bank tidak memiliki produk Bank berbasis TI | D8: Bank memiliki produk Bank berbasis TI untuk penghimpunan dan/atau penyaluran dana | E8: Bank memiliki produk Bank berbasis TI untuk penghimpunan dana, penyaluran dana, dan/atau treasury | F8: Bank memiliki produk Bank berbasis TI untuk penghimpunan dana, penyaluran dana, treasury, dan/atau aktivitas sistem pembayaran dan investasi pasar modal untuk kebutuhan domestik | G8: Bank memiliki produk Bank berbasis TI untuk penghimpunan dana, penyaluran dana, treasury, dan/atau aktivitas sistem pembayaran termasuk jual beli mata uang dan investasi pasar modal untuk kebutuhan internasional | H8: 2 | I8: Produk dana pihak ketiga, pembiayaan, kredit, tresury, sistem pembayaran dll
A9: 2.5. | B9: Bank sebagai penyedia jasa TI | C9: Bank tidak menjadi penyedia jasa TI untuk lembaga jasa keuangan lain | D9: Bank menjadi penyedia jasa TI untuk 1 atau 2 lembaga jasa keuangan lain | E9: Bank menjadi penyedia jasa TI untuk 3 lembaga jasa keuangan lain | F9: Bank menjadi penyedia jasa TI untuk 4 atau 5 lembaga jasa keuangan lain | G9: Bank menjadi penyedia jasa TI untuk lebih dari 5 lembaga jasa keuangan lain | H9: 1 | I9: Bank tidak menjadi penyedia jasa TI untuk lembaga jasa keuangan lain
G11: Avg | H11: =SUM(H5:H9)/5 -> 2.8
G12: Peringkat | H12: =IF(H11<=1,("Low"),IF(H11<=2,("Low to Moderate"),IF(H11<=3,("Moderate"),IF(H11<=4,("Moderate to High"),"High")))) -> Moderate

Sheet Karakter Organisasi
A1: C. Kertas Kerja Penilaian Risiko Inheren terkait Keamanan Siber - Karakter Organisasi
A3: 3. Karakteristik Organisasi | C3: Level Risiko | H3: Hasil Penilaian | I3: Penjelasan
C4: Low (1) | D4: Low to Moderate (2) | E4: Moderate (3) | F4: Moderate to High (4) | G4: High (5)
A5: 3.1. | B5: Pergantian (turnover) pada SDM yang menangani TI/ketahanan dan keamanan siber | C5: Persentase pergantian SDM yang menangani TI/ketahanan dan keamanan siber <5% dalam 1 tahun terakhir | D5: Persentase pergantian SDM yang menangani TI/ketahanan dan keamanan siber <10% dalam 1 tahun terakhir | E5: Persentase pergantian SDM yang menangani TI/ketahanan dan keamanan siber <15% dalam 1 tahun terakhir | F5: Persentase pergantian SDM yang menangani TI/ketahanan dan keamanan siber < 20% dalam 1 tahun terakhir | G5: Persentase pergantian SDM yang menangani TI/ketahanan dan keamanan siber ≥ 20% dalam 1 tahun terakhir | H5: 1 | I5: Tidak terjadi penggantian SDM yang menangani TI/ ketahanan dan keamanan siber
A6: 3.2. | B6: Perubahan di lingkungan TI | C6: Kurang dari 3 implementasi sistem kritikal dalam 1 tahun terakhir | D6: 3-5 implementasi sistem kritikal dalam 1 tahun terakhir | E6: 6-8 implementasi sistem kritikal dalam 1 tahun terakhir | F6: 9-11 implementasi sistem kritikal dalam 1 tahun terakhir | G6: >11 implementasi sistem kritikal dalam 1 tahun terakhir | H6: 2 | I6: Implementasi sistem kritikal dalam 1 tahun terakhir adalah FDS, SPBI dan Infrastruktur Security
A7: 3.3. | B7: Pengelolaan privilege access (administrator dan selevel administrator) di seluruh perangkat (host, jaringan,database, aplikasi, dan cloud) | C7: Seluruh privilege access untuk seluruh tipe perangkat dikelola oleh unit TI | D7: Privilege access untuk 1 atau 2 tipe perangkat dikelola oleh pihak selain unit TI | E7: Privilege access untuk 3 tipe perangkat dikelola oleh pihak selain unit TI | F7: Privelege access untuk 4 tipe perangkat dikelola oleh pihak selain unit TI | G7: Privelege access untuk lebih dari 4 tipe perangkat dikelola oleh pihak selain unit TI | H7: 1 | I7: Seluruh privilege access untuk seluruh tipe perangkat dikelola oleh Divisi Teknologi Informasi
G9: Avg | H9: =SUM(H5:H7)/3 -> 1.3333333
G10: Peringkat | H10: =IF(H9<=1,("Low"),IF(H9<=2,("Low to Moderate"),IF(H9<=3,("Moderate"),IF(H9<=4,("Moderate to High"),"High")))) -> Low to Moderate

Sheet Rekam Jejak
A1: D. Kertas Kerja Penilaian Risiko Inheren terkait Keamanan Siber - Rekam Jejak
A3: 4. Rekam Jejak Insiden Siber | C3: Level Risiko | H3: Hasil Penilaian | I3: Penjelasan
C4: Low (1) | D4: Low to Moderate (2) | E4: Moderate (3) | F4: Moderate to High (4) | G4: High (5)
A5: 4.1. | B5: Persentase insiden siber yang berdampak signifikan dalam 12 (dua belas) bulan terakhir | C5: Tidak ada insiden siber yang berdampak signifikan | D5: Hingga 30% dari total insiden siber berdampak signifikan | E5: Hingga 50% dari total insiden siber berdampak signifikan | F5: Hingga 70% dari total insiden siber berdampak signifikan | G5: Lebih dari 70% dari total insiden siber berdampak signifikan | H5: 1 | I5: Tidak ada insiden siber yang berdampak signifikan
A6: 4.2. | B6: Cakupan dampak insiden siber dalam 12 (dua belas) bulan terakhir | C6: Tidak terdapat dampak (tidak terdapat insiden siber) | D6: Insiden siber hanya berdampak pada internal Bank | E6: Insiden siber berdampak pada pihak ketiga selain nasabah | F6: Insiden siber berdampak pada ketersediaan produk Bank | G6: Insiden siber berdampak pada kerugian nasabah (contoh : kebocoran data pribadi nasabah) | H6: 1 | I6: Tidak terdapat dampak (tidak terdapat insiden siber)
G8: Avg | H8: =SUM(H5:H6)/2 -> 1
G9: Peringkat | H9: =IF(H8<=1,("Low"),IF(H8<=2,("Low to Moderate"),IF(H8<=3,("Moderate"),IF(H8<=4,("Moderate to High"),"High")))) -> Low

Sheet Matriks Inheren
A1: Matriks Penetapan Tingkat Risiko Inheren terkait Keamanan Siber
A3: Peringkat | B3: Defenisi Peringkat
A4: LOW (1) | B4: Dengan mempertimbangkan aktivitas bisnis yang dilakukan Bank, kemungkinan kerugian yang dihadapi Bank dari risiko inheren terkait keamanan siber tergolong sangat rendah selama periode waktu tertentu pada masa depan. Contoh karakteristik Bank yang termasuk dalam peringkat Low (1): a. Bank menggunakan TI yang sangat terbatas dan kerentanan terhadap serangan siber sangat rendah; b. tidak terdapat produk Bank yang disalurkan menggunakan TI dan/atau saluran daring dan mobile; c. pergantian (turnover) pada SDM yang menangani TI/ ketahanan dan keamanan siber sangat rendah; d. tidak terdapat insiden siber yang berdampak signifikan selama 12 (dua belas) bulan terakhir.
A5: LOW TO MODERATE (2) | B5: Dengan mempertimbangkan aktivitas bisnis yang dilakukan Bank, kemungkinan kerugian yang dihadapi Bank dari risiko inheren terkait keamanan siber tergolong rendah selama periode waktu tertentu pada masa depan. Contoh karakteristik Bank yang termasuk dalam peringkat Low to Moderate (2): a. Bank menggunakan TI yang terbatas, kerentanan terhadap serangan siber rendah, dan Bank melakukan outsourcing TI dengan kompleksitas yang sangat rendah; b. jenis produk Bank yang disalurkan menggunakan TI dan/atau saluran daring dan mobile sangat terbatas; c. pergantian (turnover) pada SDM yang menangani TI/ketahanan dan keamanan siber rendah; d. persentase insiden siber yang berdampak signifikan selama 12 (dua belas) bulan terakhir sangat rendah serta berdampak hanya pada intern Bank.
A6: MODERATE (3) | B6: Dengan mempertimbangkan aktivitas bisnis yang dilakukan Bank, kemungkinan kerugian yang dihadapi Bank dari risiko inheren terkait keamanan siber tergolong cukup tinggi selama periode waktu tertentu pada masa depan. Contoh karakteristik Bank yang termasuk dalam peringkat Moderate (3): a. Bank menggunakan TI yang cukup terbatas, kerentanan terhadap serangan siber cukup rendah, dan Bank melakukan outsourcing TI dengan kompleksitas yang rendah; b. jenis produk Bank yang disalurkan menggunakan TI dan/atau saluran daring dan mobile terbatas; c. pergantian (turnover) pada SDM yang menangani TI/ ketahanan dan keamanan siber cukup tinggi; d. persentase insiden siber yang berdampak signifikan selama 12 (dua belas) bulan terakhir rendah serta berdampak pada pihak ketiga selain nasabah.
A7: MODERATE TO HIGH (4) | B7: Dengan mempertimbangkan aktivitas bisnis yang dilakukan Bank, kemungkinan kerugian yang dihadapi Bank dari risiko inheren terkait keamanan siber tergolong tinggi selama periode waktu tertentu pada masa depan. Contoh karakteristik Bank yang termasuk dalam peringkat Moderate to High (4): a. Bank menggunakan TI yang kompleks dalam hal cakupan dan kecanggihannya, kerentanan terhadap serangan siber cukup tinggi, dan Bank melakukan outsourcing TI kritikal dengan kompleksitas yang cukup tinggi; b. jenis produk Bank yang disalurkan menggunakan TI dan/atau saluran daring dan mobile cukup banyak; c. pergantian (turnover) pada SDM yang menangani TI/ ketahanan dan keamanan siber tinggi; d. persentase insiden siber yang berdampak signifikan selama 12 (dua belas) bulan terakhir cukup tinggi serta berdampak pada ketersediaan produk Bank.
A8: HIGH (5) | B8: Dengan mempertimbangkan aktivitas bisnis yang dilakukan Bank, kemungkinan kerugian yang dihadapi Bank dari risiko inheren terkait keamanan siber tergolong sangat tinggi selama periode waktu tertentu pada masa depan. Contoh karakteristik Bank yang termasuk dalam peringkat High (5): a. Bank menggunakan TI yang sangat kompleks dalam hal cakupan dan kecanggihannya, kerentanan terhadap serangan siber sangat tinggi, dan Bank melakukan outsourcing TI kritikal dengan kompleksitas yang tinggi; b. jenis produk Bank yang disalurkan menggunakan TI dan/atau saluran daring dan mobile sangat tinggi; c. pergantian (turnover) pada SDM yang menangani TI/ ketahanan dan keamanan siber sangat tinggi; d. persentase insiden siber yang berdampak signifikan selama 12 (dua belas) bulan terakhir sangat tinggi serta berdampak langsung pada kerugian nasabah.

Sheet All Inheren
C3: Peringkat Risiko Inheren Kemanan Siber
C5: Inherent Risk Rating | E5: Nilai Rating | F5: Kualifikasi Rating | H5: SKALA RATING INHERENT
C6: 1 | D6: Teknologi | E6: =Teknologi!H16 -> 2.7 | F6: =Teknologi!H17 -> Moderate | H6: - LOW | I6: nilai < 2
C7: 2 | D7: Produk Bank | E7: ='Produk Bank'!H11 -> 2.8 | F7: ='Produk Bank'!H12 -> Moderate | H7: - LOW TO MODERATE | I7: 2 < nilai < 3
C8: 3 | D8: Karakteristik Organisasi | E8: ='Karakter Organisasi'!H9 -> 1.3333333 | F8: ='Karakter Organisasi'!H10 -> Low to Moderate | H8: - MODERATE | I8: 3 < nilai < 4
C9: 4 | D9: Rekam Jejak Insiden Siber | E9: ='Rekam Jejak'!H8 -> 1 | F9: ='Rekam Jejak'!H9 -> Low | H9: - MODERATE TO HIGH | I9: 4 < nilai < 5
E10: =SUM(E6:E9)/4 -> 1.9583333 | F10: =IF(E10<=1,("Low"),IF(E10<=2,("Low to Moderate"),IF(E10<=3,("Moderate"),IF(E10<=4,("Moderate to High"),"High")))) -> Low to Moderate | H10: - HIGH | I10: nilai > 5

Sheet KPMR
A1: E. Kertas Kerja Penilaian Kualitas Penerapan Manajemen Risiko terkait Keamanan Siber
A3: No | B3: Domain | C3: Sub Domain | D3: Kontrol | E3: Penerapan Kontrol | F3: Penjelasan | G3: Referensi Dokumen | H3: Departemen/Unit/Jabatan yang Bertanggung Jawab
A4: 1 | B4: Tata Kelola Risiko terkait Keamanan Siber | C4: 1.1. Kecukupan Pengawasan Aktif oleh Direksi dan Dewan Komisaris | D4: 1.1.a. Bank menetapkan wewenang dan tanggung jawab Direksi terkait dengan penerapan manajemen risiko terkait keamanan siber. | E4: 2 | F4: Bank telah memiliki ketentuan mengenai penerapan manajemen risiko terkait ketahanan dan keamanan siber | G4: 1. Peraturan PT Bank Sumut No. 008/Dir/DMR-MROL/PBS/2025 tanggal 29 Desember 2025 perihal Pedoman Penerapan Ketahahan dan Keamaman Siber 2. Surat Keputusan Direksi No. 278/Dir/DMR-MROL/SK/2025 tanggal 29 Desember 2025 tentang Pengujian Keamanan Siber PT Bank Sumut; 3. Surat Kepautusan Direksi No. 279/Dir/DMR-MROL/SK/2025 tanggal 29 Desember 2025 tentang Manajemen Proses Penanggulangan dan Pemulihan Insiden Siber PT Bank Sumut 4. Surat Edaran Direksi No. 138/Dir/DMR-MROL/SE/2025 tanggal 29 Desember 2025 perihal Petunjuk Pelaksanaan Pengujian Keamaman Siber; 5. Surat Edaran Direksi No. 139/DIr/DMR-MROL/SE/2025 tanggal 29 Desember 2025 perihal Pelaksanaan Manajemen Proses Penanggulangan dan Pemulihan Insiden Siber pada PT Bank Sumut | H4: DMR
D5: 1.1.b. Bank menetapkan wewenang dan tanggung jawab Dewan Komisaris terkait dengan penerapan manajemen risiko terkait keamanan siber. | E5: 2 | F5: Bank telah memiliki ketentuan mengenai penerapan manajemen risiko terkait keamanan siber | G5: 1. Peraturan PT Bank Sumut No. 008/Dir/DMR-MROL/PBS/2025 tanggal 29 Desember 2025 perihal Pedoman Penerapan Ketahahan dan Keamaman Siber 2. Surat Keputusan Direksi No. 278/Dir/DMR-MROL/SK/2025 tanggal 29 Desember 2025 tentang Pengujian Keamanan Siber PT Bank Sumut; 3. Surat Kepautusan Direksi No. 279/Dir/DMR-MROL/SK/2025 tanggal 29 Desember 2025 tentang Manajemen Proses Penanggulangan dan Pemulihan Insiden Siber PT Bank Sumut 4. Surat Edaran Direksi No. 138/Dir/DMR-MROL/SE/2025 tanggal 29 Desember 2025 perihal Petunjuk Pelaksanaan Pengujian Keamaman Siber; 5. Surat Edaran Direksi No. 139/DIr/DMR-MROL/SE/2025 tanggal 29 Desember 2025 perihal Pelaksanaan Manajemen Proses Penanggulangan dan Pemulihan Insiden Siber pada PT Bank Sumut | H5: DMR
C6: 1.2. Perumusan Tingkat Risiko yang Akan Diambil (Risk Appetite) dan Toleransi Risiko (Risk Tolerance) terkait Keamanan Siber | D6: 1.2.a. Direksi bertanggung jawab untuk menetapkan tingkat risiko yang diambil (risk appetite) terkait keamanan siber Bank. | E6: 2 | F6: saat ini ketahanan Siber menjadi salah satu parameter dalam Risk Appetite Bank | G6: Monitoring Risk Appetite Statement yang disampaikan pada laporan portofolio risiko | H6: DMR
D7: 1.2.b. Direksi bertanggung jawab untuk menetapkan toleransi risiko (risk tolerance) terkait keamanan siber Bank. | E7: 2 | F7: saat ini ketahanan Siber menjadi salah satu paramter dalam Risk Appetite Bank | G7: Monitoring Risk Appetite Statement yang disampaikan pada laporan portofolio risiko | H7: DMR
C8: 1.3. Budaya dan Kesadaran Risiko terkait Keamanan Siber | D8: 1.3.a. Direksi mengembangkan budaya mengenai tanggung jawab terkait keamanan siber bagi pegawai di semua level. | E8: 2 | F8: secara umum Bank telah melakukan kampanye baik kepada nasabah maupun kepada internal Bank terkait dengan keamanan siber | G8: Vidio edukasi yang diupload pada instagram Bank Sumutnews | H8: DMR, SEKPER, DTI, DSDM
D9: 1.3.b. Direksi membangun dan memelihara kesadaran dan komitmen yang kuat terhadap keamanan siber Bank. | E9: 2 | F9: secara umum Bank telah melakukan kampanye baik kepada nasabah maupun kepada internal Bank terkait dengan keamanan siber | G9: Vidio edukasi yang diupload pada instagram Bank Sumutnews dan melakukan evaluasi pemahaman melalui aplikasi Learning Management System (LMS) | H9: DMR, SEKPER, DTI
D10: 1.3.c. Bank memastikan efektivitas pemahaman dan penerapan kebijakan keamanan siber bagi seluruh pegawai dan pemangku kepentingan terkait. | E10: 2 | F10: Melakukan sosialisasi simulasi kepada seluruh pegawai terkait pemahaman akan terjadi serangan siber | G10: Meningkatkan pemahaman melalui aplikasi Learning Management System (LMS) | H10: DMR dan DTI
A11: 2 | B11: Kerangka Manajemen Risiko terkait Keamanan Siber | C11: 2.1. Strategi Manajemen Risiko terkait Keamanan Siber | D11: 2.1.a. Bank merumuskan strategi manajemen risiko terkait keamanan siber yang sepadan dengan kerentanan dan tingkat eksposur Bank terhadap ancaman siber serta sejalan dengan tingkat risiko yang akan diambil (risk appetite) dan toleransi risiko (risk tolerance) terkait keamanan siber serta strategi bisnis secara keseluruhan. | E11: 2 | F11: Sudah memiliki ketentuan mengenai penerapan manajemen risiko keamanan siber, dan akan melakukan evaluasi sesuai dengan perkembangannya. | G11: 1. Peraturan PT Bank Sumut No. 008/Dir/DMR-MROL/PBS/2025 tanggal 29 Desember 2025 perihal Pedoman Penerapan Ketahahan dan Keamaman Siber 2. Surat Keputusan Direksi No. 278/Dir/DMR-MROL/SK/2025 tanggal 29 Desember 2025 tentang Pengujian Keamanan Siber PT Bank Sumut; 3. Surat Kepautusan Direksi No. 279/Dir/DMR-MROL/SK/2025 tanggal 29 Desember 2025 tentang Manajemen Proses Penanggulangan dan Pemulihan Insiden Siber PT Bank Sumut 4. Surat Edaran Direksi No. 138/Dir/DMR-MROL/SE/2025 tanggal 29 Desember 2025 perihal Petunjuk Pelaksanaan Pengujian Keamaman Siber; 5. Surat Edaran Direksi No. 139/DIr/DMR-MROL/SE/2025 tanggal 29 Desember 2025 perihal Pelaksanaan Manajemen Proses Penanggulangan dan Pemulihan Insiden Siber pada PT Bank Sumut | H11: DMR
D12: 2.1.b. Bank memastikan kejelasan seluruh peran dan tanggung jawab terkait keamanan siber dalam strategi manajemen risiko terkait keamanan siber. | E12: 1 | F12: Sudah memiliki fungsi siber yang independen dari fungsi TI Bank pada Divisi Manajemen Risiko, dan sudah memiliki ketentuan mengenai ketahanan dan keamanan siber serta secara internal Divisi Teknologi Informasi juga memiliki bidang security IT | G12: 1. Peraturan PT Bank Sumut No. 008/Dir/DMR-MROL/PBS/2025 tanggal 29 Desember 2025 perihal Pedoman Penerapan Ketahahan dan Keamaman Siber 2. Surat Keputusan Direksi No. 278/Dir/DMR-MROL/SK/2025 tanggal 29 Desember 2025 tentang Pengujian Keamanan Siber PT Bank Sumut; 3. Surat Kepautusan Direksi No. 279/Dir/DMR-MROL/SK/2025 tanggal 29 Desember 2025 tentang Manajemen Proses Penanggulangan dan Pemulihan Insiden Siber PT Bank Sumut 4. Surat Edaran Direksi No. 138/Dir/DMR-MROL/SE/2025 tanggal 29 Desember 2025 perihal Petunjuk Pelaksanaan Pengujian Keamaman Siber; 5. Surat Edaran Direksi No. 139/DIr/DMR-MROL/SE/2025 tanggal 29 Desember 2025 perihal Pelaksanaan Manajemen Proses Penanggulangan dan Pemulihan Insiden Siber pada PT Bank Sumut 5. Profil Jabatan Divisi Manajemen Risiko Bidang Manajemen Risiko Operasional 6. Struktur Organisasi Divisi Teknologi Informasi 7. SK No. 214 /Dir/DMR-MROL/SK/2024 tanggal 21 Oktober 2024 tentang Tim Tanggap Insiden Siber PT Bank Sumut | H12: DMR
D13: 2.1.c. Direksi mengomunikasikan strategi manajemen risiko terkait keamanan siber secara efektif kepada seluruh satuan kerja dan pegawai agar dipahami secara jelas. | E13: 2 | F13: Mendukung adanya sosialisasi terkait dengan keamanan siber, serta pertemuan untuk membahas mengenai siber dan akan melaksanakan risk awarness terkait keamanan siber | G13: Melakukan Sosialisasi | H13: DMR
D14: 2.1.d. Direksi melakukan kaji ulang strategi manajemen risiko terkait keamanan siber secara berkala untuk menentukan perlu atau tidaknya dilakukan perubahan terhadap strategi manajemen risiko tersebut. | E14: 3 | F14: Mendukung adanya sosialisasi terkait dengan keamanan siber, serta pertemuan untuk membahas mengenai siber dan akan melaksanakan risk awarness terkait keamanan siber | H14: DMR
C15: 2.2. Kecukupan Perangkat Organisasi terkait Keamanan Siber | D15: 2.2.a. Direksi memastikan struktur organisasi Bank telah disertai dengan kejelasan tugas dan tanggung jawab mengenai penerapan manajemen risiko terkait keamanan siber pada seluruh satuan kerja yang disesuaikan dengan tujuan dan kebijakan usaha serta ukuran dan kompleksitas kegiatan usaha Bank | E15: 1 | F15: Sudah memiliki fungsi siber yang independen dari fungsi TI bank pada Divisi Manajemen Risiko dan fungsi security IT pada Divisi Teknologi Informasi | G15: 1. Peraturan PT Bank Sumut No. 008/Dir/DMR-MROL/PBS/2025 tanggal 29 Desember 2025 perihal Pedoman Penerapan Ketahahan dan Keamaman Siber 2. Surat Keputusan Direksi No. 278/Dir/DMR-MROL/SK/2025 tanggal 29 Desember 2025 tentang Pengujian Keamanan Siber PT Bank Sumut; 3. Surat Kepautusan Direksi No. 279/Dir/DMR-MROL/SK/2025 tanggal 29 Desember 2025 tentang Manajemen Proses Penanggulangan dan Pemulihan Insiden Siber PT Bank Sumut 4. Surat Edaran Direksi No. 138/Dir/DMR-MROL/SE/2025 tanggal 29 Desember 2025 perihal Petunjuk Pelaksanaan Pengujian Keamaman Siber; 5. Surat Edaran Direksi No. 139/DIr/DMR-MROL/SE/2025 tanggal 29 Desember 2025 perihal Pelaksanaan Manajemen Proses Penanggulangan dan Pemulihan Insiden Siber pada PT Bank Sumut 5. Profil Jabatan Divisi Manajemen Risiko Bidang Manajemen Risiko Operasional 6. Struktur Organisasi Divisi Teknologi Informasi 7. SK No. 214 /Dir/DMR-MROL/SK/2024 tanggal 21 Oktober 2024 tentang Tim Tanggap Insiden Siber PT Bank Sumut | H15: DMR
D16: 2.2.b. Struktur organisasi dirancang untuk memastikan bahwa satuan kerja yang melakukan fungsi pengendalian intern terhadap manajemen risiko terkait keamanan siber memiliki independensi terhadap satuan kerja bisnis. | E16: 1 | F16: Sudah memiliki fungsi siber yang independen dari fungsi TI bank pada Divisi Manajemen Risiko | G16: 1. SK No. 218/Dir/DMR-MRO/SK/2023 tanggal 29 Desember 2023 tentang Ketahanan dan Keamanan Siber 2. SE No. 130/Dir/DMR-MRO/SE/2023 tanggal 29 Desember 2023 perihal Ketentuan Pelaksanaan Mengenai Ketahanan dan Keamanan Siber PT Bank Sumut 3. Profil Jabatan Divisi Manajemen Risiko Bidang Manajemen Risiko Operasional 4. Struktur Organisasi Divisi Teknologi Informasi | H16: DMR
D17: 2.2.c. Bank memastikan satuan kerja manajemen risiko memiliki fungsi yang menangani penerapan manajemen risiko terkait keamanan siber | E17: 2 | F17: Sudah memiliki fungsi siber yang independen dari fungsi TI bank pada Divisi Manajemen Risiko | G17: '1. Peraturan PT Bank Sumut No. 008/Dir/DMR-MROL/PBS/2025 tanggal 29 Desember 2025 perihal Pedoman Penerapan Ketahahan dan Keamaman Siber 2. Surat Keputusan Direksi No. 278/Dir/DMR-MROL/SK/2025 tanggal 29 Desember 2025 tentang Pengujian Keamanan Siber PT Bank Sumut; 3. Surat Kepautusan Direksi No. 279/Dir/DMR-MROL/SK/2025 tanggal 29 Desember 2025 tentang Manajemen Proses Penanggulangan dan Pemulihan Insiden Siber PT Bank Sumut 4. Surat Edaran Direksi No. 138/Dir/DMR-MROL/SE/2025 tanggal 29 Desember 2025 perihal Petunjuk Pelaksanaan Pengujian Keamaman Siber; 5. Surat Edaran Direksi No. 139/DIr/DMR-MROL/SE/2025 tanggal 29 Desember 2025 perihal Pelaksanaan Manajemen Proses Penanggulangan dan Pemulihan Insiden Siber pada PT Bank Sumut 5. Profil Jabatan Divisi Manajemen Risiko Bidang Manajemen Risiko Operasional 6. Struktur Organisasi Divisi Teknologi Informasi 7. SK No. 214 /Dir/DMR-MROL/SK/2024 tanggal 21 Oktober 2024 tentang Tim Tanggap Insiden Siber PT Bank Sumut | H17: DMR
D18: 2.2.d. Bank memiliki unit atau fungsi yang bertugas menangani ketahanan dan keamanan siber. | E18: 1 | F18: Sudah memiliki fungsi siber yang independen dari fungsi TI bank pada Divisi Manajemen Risiko | G18: 1. SK No. 218/Dir/DMR-MRO/SK/2023 tanggal 29 Desember 2023 tentang Ketahanan dan Keamanan Siber 2. SE No. 130/Dir/DMR-MRO/SE/2023 tanggal 29 Desember 2023 perihal Ketentuan Pelaksanaan Mengenai Ketahanan dan Keamanan Siber PT Bank Sumut 3. Profil Jabatan Divisi Manajemen Risiko Bidang Manajemen Risiko Operasional 4. Struktur Organisasi Divisi Teknologi Informasi 5. SK No. 214 /Dir/DMR-MROL/SK/2024 tanggal 21 Oktober 2024 tentang Tim Tanggap Insiden Siber PT Bank Sumut | H18: DMR
C19: 2.3. Kecukupan Kebijakan, Prosedur, dan Penetapan Limit Risiko terkait Keamanan Siber | D19: 2.3.a. Direksi menetapkan kebijakan dan prosedur yang dituangkan secara tertulis dalam menerapkan manajemen risiko terkait keamanan siber dan ketahanan siber. | E19: 2 | F19: Divisi Manajemen Risiko menerbitkan ketentuan mengenai katahanan dan keamanan siber | G19: 1. Peraturan PT Bank Sumut No. 008/Dir/DMR-MROL/PBS/2025 tanggal 29 Desember 2025 perihal Pedoman Penerapan Ketahahan dan Keamaman Siber 2. Surat Keputusan Direksi No. 278/Dir/DMR-MROL/SK/2025 tanggal 29 Desember 2025 tentang Pengujian Keamanan Siber PT Bank Sumut; 3. Surat Kepautusan Direksi No. 279/Dir/DMR-MROL/SK/2025 tanggal 29 Desember 2025 tentang Manajemen Proses Penanggulangan dan Pemulihan Insiden Siber PT Bank Sumut 4. Surat Edaran Direksi No. 138/Dir/DMR-MROL/SE/2025 tanggal 29 Desember 2025 perihal Petunjuk Pelaksanaan Pengujian Keamaman Siber; 5. Surat Edaran Direksi No. 139/DIr/DMR-MROL/SE/2025 tanggal 29 Desember 2025 perihal Pelaksanaan Manajemen Proses Penanggulangan dan Pemulihan Insiden Siber pada PT Bank Sumut | H19: DMR
D20: 2.3.b. Bank mendesain dan mengimplementasikan kebijakan dan prosedur dengan memperhatikan karakteristik dan kompleksitas kegiatan usaha, tingkat risiko yang akan diambil (risk appetite) dan toleransi risiko (risk tolerance), profil risiko, serta peraturan yang ditetapkan otoritas terkait dengan keamanan siber. | E20: 2 | F20: Divisi Manajemen Risiko menerbitkan ketentuan mengenai katahanan dan keamanan siber serta menetapkan Risk Appetite Statement (RAS) dan melakukan pemantauan terhadap RAS dimaksud | G20: 1. Peraturan PT Bank Sumut No. 008/Dir/DMR-MROL/PBS/2025 tanggal 29 Desember 2025 perihal Pedoman Penerapan Ketahahan dan Keamaman Siber 2. Surat Keputusan Direksi No. 278/Dir/DMR-MROL/SK/2025 tanggal 29 Desember 2025 tentang Pengujian Keamanan Siber PT Bank Sumut; 3. Surat Kepautusan Direksi No. 279/Dir/DMR-MROL/SK/2025 tanggal 29 Desember 2025 tentang Manajemen Proses Penanggulangan dan Pemulihan Insiden Siber PT Bank Sumut 4. Surat Edaran Direksi No. 138/Dir/DMR-MROL/SE/2025 tanggal 29 Desember 2025 perihal Petunjuk Pelaksanaan Pengujian Keamaman Siber; 5. Surat Edaran Direksi No. 139/DIr/DMR-MROL/SE/2025 tanggal 29 Desember 2025 perihal Pelaksanaan Manajemen Proses Penanggulangan dan Pemulihan Insiden Siber pada PT Bank Sumut 6. Monitoring Risk Appetite Statement | H20: DMR
D21: 2.3.c. Bank melakukan internalisasi kebijakan manajemen risiko terkait keamanan siber, termasuk strategi dan tujuan manajemen risiko terkait keamanan siber, ke dalam proses bisnis pada seluruh lini bisnis dan aktivitas pendukung, termasuk kebijakan yang bersifat spesifik sesuai dengan kebutuhan lini bisnis dan aktivitas pendukung Bank. | E21: 2 | F21: Divisi Manajemen Risiko menerbitkan ketentuan mengenai keamanan siber dan telah memiliki fungsi siber pada job desc, serta akan membentuk tim tanggap insiden siber | G21: Divisi Manajemen Risiko telah melakukan analisa siber terhadap produk-produk maupun layanan yang akan diimplementasikan contoh analisa siber terhadap API, Sumut Mobile, Internet Banking dll | H21: DMR
D22: 2.3.d. Bank menyusun kebijakan manajemen risiko terkait keamanan siber yang memadai. | E22: 1 | F22: Bank telah memiliki ketentuan mengenai penerapan manajemen risiko terkait ketahanan dan keamanan siber | G22: 1. SK No. 218/Dir/DMR-MRO/SK/2023 tanggal 29 Desember 2023 tentang Ketahanan dan Keamanan Siber 2. SE No. 130/Dir/DMR-MRO/SE/2023 tanggal 29 Desember 2023 perihal Ketentuan Pelaksanaan Mengenai Ketahanan dan Keamanan Siber PT Bank Sumut | H22: DMR
D23: 2.3.e. Bank memiliki prosedur yang merupakan turunan dari kebijakan manajemen risiko terkait keamanan siber, yang dapat berupa pengendalian yang bersifat umum pada seluruh lini bisnis dan aktivitas pendukung Bank dan kontrol yang bersifat spesifik pada masing-masing lini bisnis dan aktivitas pendukung Bank. | E23: 2 | F23: Bank akan menerbitkan ketentuan turunan untuk mendukung keamanan siber | G23: 1. SE No. 115/Dir/DMR-MROL/SE/2024 tanggal 24 September 2024 tentang Pedoman Pelaksanaan Manajemen Insiden Keamanan Informasi/Siber serta Proses Penanggulangan dan Pemulihan Insiden Siber Pada PT Bank Sumut | H23: DMR
D24: 2.3.f. Bank memiliki kebijakan dan prosedur keamanan siber yang digunakan untuk mengatur pelindungan aset TI. | E24: 2 | F24: Bank akan menerbitkan ketentuan turunan untuk mendukung keamanan siber | G24: SMKI SK/SE Pengelolaan Aset Teknologi Informasi | H24: DMR
D25: 2.3.g. Bank memiliki kebijakan dan prosedur manajemen risiko terkait keamanan siber untuk pihak ketiga dan subkontraktor dari pihak ketiga yang mengatur tentang pengelolaan data/informasi digital milik Bank termasuk data nasabah yang dimiliki Bank) oleh pihak ketiga dan subkontraktor dari pihak ketiga. | E25: 2 | F25: Bank akan menerbitkan ketentuan turunan untuk mendukung keamanan siber | G25: Diatur dalam ketentuan Sistem Manajemen Keamanan Informasi (SMKI) | H25: DMR
D26: 2.3.h. Bank menerapkan manajemen risiko terkait keamanan siber untuk pihak ketiga dan subkontraktor dari pihak ketiga. | E26: 3 | F26: Bank akan menerbitkan ketentuan turunan untuk mendukung keamanan siber | G26: saat ini masih diatur secara umum dalam ketentuan Pengadaan Barang dan Jasa | H26: DMR
D27: 2.3.i. Bank menetapkan standar minimum kendali keamanan siber bagi pihak ketiga dan subkontraktor dari pihak ketiga, yaitu: 1) ketentuan kerahasiaan di kontrak kerja sama; 2) ketersediaan tata kelola pengamanan siber di pihak ketiga dan subkontraktor dari pihak ketiga (kebijakan, prosedur, ketentuan, dan lainnya); dan 3) pengelolaan risiko terkait keamanan siber termasuk manajemen insiden siber di pihak ketiga dan subkontraktor dari pihak ketiga | E27: 3 | F27: Bank akan menerbitkan ketentuan turunan untuk mendukung keamanan siber | G27: Diatur dalam ketentuan Sistem Manajemen Keamanan Informasi (SMKI) dan secara umum diatur dalam ketentuan Pengadaan Barang dan Jasa | H27: DMR
D28: 2.3.j. Bank memiliki limit risiko terkait keamanan siber yang sesuai dengan tingkat risiko yang akan diambil (risk appetite), toleransi risiko (risk tolerance), dan strategi Bank terkait keamanan siber secara keseluruhan serta dengan memperhatikan kemampuan Bank untuk dapat menyerap eksposur risiko terkait keamanan siber atau kerugian yang timbul, pengalaman kerugian di masa lalu, kemampuan SDM, dan kepatuhan terhadap ketentuan eksternal yang berlaku. | E28: 2 | F28: Sudah memiliki ketentuan mengenai penerapan manajemen risiko keamanan siber, dan akan melakukan evaluasi sesuai dengan perkembangannya. | G28: '1. Peraturan PT Bank Sumut No. 008/Dir/DMR-MROL/PBS/2025 tanggal 29 Desember 2025 perihal Pedoman Penerapan Ketahahan dan Keamaman Siber 2. Surat Keputusan Direksi No. 278/Dir/DMR-MROL/SK/2025 tanggal 29 Desember 2025 tentang Pengujian Keamanan Siber PT Bank Sumut; 3. Surat Kepautusan Direksi No. 279/Dir/DMR-MROL/SK/2025 tanggal 29 Desember 2025 tentang Manajemen Proses Penanggulangan dan Pemulihan Insiden Siber PT Bank Sumut 4. Surat Edaran Direksi No. 138/Dir/DMR-MROL/SE/2025 tanggal 29 Desember 2025 perihal Petunjuk Pelaksanaan Pengujian Keamaman Siber; 5. Surat Edaran Direksi No. 139/DIr/DMR-MROL/SE/2025 tanggal 29 Desember 2025 perihal Pelaksanaan Manajemen Proses Penanggulangan dan Pemulihan Insiden Siber pada PT Bank Sumut 6. SK No. 147/Dir/DMR-MRO/SK/2023 tentang Insiden Teknologi Informasi PT Bank Sumut 7. SE No. 088/Dir/DMR-MRO/SE/2023 tanggal 16 Oktober 2023 perihal Tata Cara Pelaporan Kejadian Kritis, Penyalahgunaan dan atau Kejahatan Dalam Penyelenggaraan Teknologi Informasi PT Bank Sumut | H28: DMR
D29: 2.3.k. Kebijakan, prosedur, dan limit dalam penerapan manajemen risiko terkait keamanan siber harus didokumentasikan secara memadai dan dikomunikasikan kepada seluruh pegawai. | E29: 2 | F29: Sudah memiliki ketentuan mengenai penerapan manajemen risiko ketahanan dan keamanan siber, dan Insiden TI serta melakukan evaluasi sesuai dengan perkembangannya. | H29: DMR
D30: 2.3.l. Direksi melakukan kaji ulang atas kebijakan, prosedur, dan limit dalam penerapan manajemen risiko terkait keamanan siber secara berkala untuk menyesuaikan dengan kondisi terkini. | E30: 2 | F30: Sudah dilakukan kaji ulang/review terhadap ketentuan siber diakhir tahun 2023 | G30: ketentuan Lama '1. SK No. 218/Dir/DMR-MRO/SK/2023 tanggal 29 Desember 2023 tentang Ketahanan dan Keamanan Siber 2. SE No. 130/Dir/DMR-MRO/SE/2023 tanggal 29 Desember 2023 perihal Ketentuan Pelaksanaan Mengenai Ketahanan dan Keamanan Siber PT Bank Sumu Ketentuan baru '1. Peraturan PT Bank Sumut No. 008/Dir/DMR-MROL/PBS/2025 tanggal 29 Desember 2025 perihal Pedoman Penerapan Ketahahan dan Keamaman Siber 2. Surat Keputusan Direksi No. 278/Dir/DMR-MROL/SK/2025 tanggal 29 Desember 2025 tentang Pengujian Keamanan Siber PT Bank Sumut; 3. Surat Kepautusan Direksi No. 279/Dir/DMR-MROL/SK/2025 tanggal 29 Desember 2025 tentang Manajemen Proses Penanggulangan dan Pemulihan Insiden Siber PT Bank Sumut 4. Surat Edaran Direksi No. 138/Dir/DMR-MROL/SE/2025 tanggal 29 Desember 2025 perihal Petunjuk Pelaksanaan Pengujian Keamaman Siber; 5. Surat Edaran Direksi No. 139/DIr/DMR-MROL/SE/2025 tanggal 29 Desember 2025 perihal Pelaksanaan Manajemen Proses Penanggulangan dan Pemulihan Insiden Siber pada PT Bank Sumut | H30: DMR
A31: 3 | B31: Proses Manajemen Risiko, Kecukupan SDM, dan Kecukupan Sistem Informasi Manajemen Risiko, terkait Keamanan Siber | C31: 3.1. Proses Manajemen Risiko terkait Keamanan Siber (Identifikasi, Pengukuran, Pemantauan, dan Pengendalian) | D31: 3.1.a. Bank melaksanakan identifikasi seluruh risiko terkait keamanan siber secara berkala. | E31: 2 | F31: Bank melakukan analisa risiko siber pada produk digital/elektronik Bank | G31: Divisi Manajemen Risiko telah melakukan analisa siber terhadap produk-produk maupun layanan yang akan diimplementasikan contoh analisa siber terhadap API, Sumut Mobile, Internet Banking dll | H31: DMR dan DTI
D32: 3.1.b. Bank memastikan tersedianya metode atau sistem untuk melakukan identifikasi risiko pada seluruh kegiatan Bank yang terkait dengan keamanan siber | E32: 2 | F32: Bank melakukan analisa risiko siber pada produk digital/elektronik Bank | G32: Divisi Manajemen Risiko telah melakukan analisa siber terhadap produk-produk maupun layanan yang akan diimplementasikan contoh analisa siber terhadap API, Sumut Mobile, Internet Banking dll | H32: DMR
D33: 3.1.c. Bank melakukan pengukuran risiko secara berkala untuk seluruh kegiatan Bank yang terkait dengan keamanan siber. | E33: 2 | F33: Bank melakukan analisa risiko siber pada produk digital/elektronik Bank | G33: Divisi Manajemen Risiko telah melakukan analisa siber terhadap produk-produk maupun layanan yang akan diimplementasikan contoh analisa siber terhadap API, Sumut Mobile, Internet Banking dll | H33: DMR dan DTI
D34: 3.1.d. Bank memiliki sistem pengukuran risiko untuk mengukur eksposur risiko terkait keamanan siber pada Bank sebagai acuan untuk melakukan pengendalian. | E34: 2 | F34: Bank melakukan analisa risiko siber pada produk digital/elektronik Bank | G34: Divisi Manajemen Risiko telah melakukan analisa siber terhadap produk-produk maupun layanan yang akan diimplementasikan contoh analisa siber terhadap API, Sumut Mobile, Internet Banking dll | H34: DMR dan DTI
D35: 3.1.e. Bank melakukan evaluasi dan penyempurnaan atas sistem pengukuran risiko terkait keamanan siber secara berkala atau sewaktu-waktu dalam hal diperlukan untuk memastikan kesesuaian asumsi, akurasi, kewajaran dan integritas data, serta prosedur yang digunakan untuk mengukur risiko terkait keamanan siber. | E35: 3 | F35: Dalam proses untuk pengembangan terkait manajemen risiko teknologi informasi yang didalamnya terdapat ketahanan dan keamanan siber | H35: DMR dan DTI
D36: 3.1.f. Bank memiliki sistem dan prosedur pemantauan risiko terkait keamanan siber yang antara lain mencakup pemantauan risiko terkait keamanan siber terhadap besarnya eksposur risiko, toleransi risiko (risk tolerance), kepatuhan limit intern, dan hasil stress test maupun konsistensi pelaksanaan dengan kebijakan dan prosedur yang ditetapkan. | E36: 3 | F36: Dalam proses untuk pengembangan terkait manajemen risiko teknologi informasi yang didalamnya terdapat ketahanan dan keamanan siber | H36: DMR dan DTI
D37: 3.1.g. Bank menyiapkan suatu sistem dan prosedur back-up yang efektif untuk mencegah terjadinya gangguan dalam proses pemantauan risiko terkait keamanan siber dan melakukan pengecekan serta penilaian kembali secara berkala terhadap sistem back-up tersebut. | E37: 3 | F37: Dalam proses untuk pengembangan terkait manajemen risiko teknologi informasi yang didalamnya terdapat ketahanan dan keamanan siber | H37: DMR dan DTI
D38: 3.1.h. Bank memiliki sistem pengendalian risiko terkait keamanan siber yang memadai dengan mengacu pada kebijakan dan prosedur yang telah ditetapkan. | E38: 2 | F38: Dalam proses untuk pengembangan terkait manajemen risiko teknologi informasi yang didalamnya terdapat ketahanan dan keamanan siber | G38: 1. SK No. 214 /Dir/DMR-MROL/SK/2024 tanggal 21 Oktober 2024 tentang Tim Tanggap Insiden Siber PT Bank Sumut 2. Bank telah memiliki sistem monitoring (SOC+SIEM) terhadap risiko keamanan siber | H38: DMR dan DTI
C39: 3.2. Kecukupan SDM terkait Keamanan Siber | D39: 3.2.a. Direksi memastikan kecukupan kuantitas dan kualitas SDM yang ada di Bank dan memastikan SDM dimaksud memahami tugas dan tanggung jawabnya dalam pelaksanaan manajemen risiko terkait keamanan siber, baik untuk unit bisnis, satuan kerja manajemen risiko, maupun unit pendukung yang bertanggung jawab atas pelaksanaan manajemen risiko terkait keamanan siber. | E39: 2 | F39: Saat ini SDM terkait keamanan siber masih terbatas, namun tetap melakukan peningkatan kualitas melalui diklat | H39: DSDM
D40: 3.2.b. Direksi mengembangkan sistem penerimaan, pengembangan, dan pelatihan pegawai, termasuk rencana suksesi manajerial serta remunerasi yang memadai untuk memastikan tersedianya pegawai yang kompeten di bidang manajemen risiko terkait keamanan siber. | E40: 3 | F40: Melaksanakan sosialisasi dan diklat untuk menambah kompentensi SDM dibidang siber menambahkan standar kompetensi, sertifikasi | H40: DSDM
D41: 3.2.c. Direksi memastikan bahwa seluruh SDM memiliki pemahaman yang memadai atas risiko terkait keamanan siber dan mampu mengomunikasikan implikasi risiko terkait keamanan siber kepada Direksi, Dewan Komisaris, manajemen, dan nasabah. | E41: 2 | F41: Melaksanakan sosialisasi dan diklat untuk menambah kompentensi SDM dibidang siber | H41: DSDM
D42: 3.2.d. Direksi memastikan agar seluruh SDM memahami strategi, tingkat risiko terkait keamanan siber yang akan diambil (risk appetite) dan toleransi risiko (risk tolerance) terkait keamanan siber, kerangka manajemen risiko terkait keamanan siber yang telah ditetapkan oleh Direksi dan disetujui oleh Dewan Komisaris, serta memastikan seluruh SDM menerapkannya secara konsisten dalam aktivitas yang ditangani. | E42: 2 | G42: Ketetuan SMKI Ketetuan Manajemen Risiko Siber Laporan Simulasi Penanganan insiden siber dengan metode table top dan hasil evaluasi pemahaman risiko siber | H42: DSDM
D43: 3.2.e. Bank memiliki informasi yang utuh mengenai seluruh pegawai Bank, yang meliputi pengetahuan, keterampilan, kemampuan, dan karakter dari pegawai. | E43: 1 | F43: Sudah memiliki database pegawai, sebagai informasi pegawai menyeluruh dan Portal Divisi Teknologi Informasi terkait informasi | G43: Aplikasi kepegawaian E Best Aplikasi portal DTI | H43: DSDM
D44: 3.2.f. Bank mengembangkan dan mengimplementasikan program berkelanjutan untuk peningkatan kapasitas terkait keamanan siber kepada seluruh pegawai yang relevan, termasuk level Direksi, Dewan Komisaris, dan manajemen untuk memastikan bahwa setiap pegawai memiliki kompetensi dan keahlian untuk menjalankan peran dan tanggung jawab secara efektif. | E44: 2 | F44: Melaksanakan sosialisasi dan diklat untuk menambah kompentensi SDM dibidang siber | G44: Laporan sosialisasi Campaign Siber Media Sosial | H44: DSDM
D45: 3.2.g. Bank melakukan analisis kesenjangan (gap analysis) untuk memahami tingkat pengetahuan dan kemampuan pegawai terkait keamanan siber dan menggunakan informasi tersebut untuk membuat rencana aksi peningkatan kapasitas pegawai. | E45: 2 | F45: Sudah dilakukan dengan metode test atau ujian yang diikuti oleh seluruh level pegawai | H45: DSDM
C46: 3.3. Kecukupan Sistem Informasi Manajemen Risiko terkait Keamanan Siber | D46: 3.3.a. Bank memiliki sistem informasi manajemen risiko terkait keamanan siber dan mengembangkannya sesuai dengan kebutuhan Bank dalam rangka penerapan manajemen risiko terkait keamanan siber yang efektif. | E46: 2 | F46: Bank memiliki tools perimeter security seperti next generation firewall, web application firewall, endpoint security. Bank juga memiliki tools detection & response atas security seperti SOC, FDS dll. Implementasi tools security dilakukan dalam rangka penerapan manajemen risiko terkait dengan pengamanan sistem dalam rangka keamanan siber yang efektif | H46: DTI
D47: 3.3.b. Bank memastikan sistem informasi manajemen risiko terkait keamanan siber dan informasi yang dihasilkan telah sesuai dengan karakteristik dan kompleksitas kegiatan usaha Bank serta adaptif terhadap perubahan. | E47: 2 | F47: Tools security yang saat ini dimiliki dinilai masih cukup efektif untuk skalabilitas dan kompleksitas kegiatan usaha bank dan dinilai adaptif terhadap perubahan | H47: DTI
D48: 3.3.c. Bank melakukan kaji ulang secara berkala atas kecukupan cakupan informasi yang dihasilkan dari sistem informasi manajemen risiko terkait keamanan siber untuk memastikan bahwa cakupan informasi tersebut telah memadai sesuai perkembangan tingkat kompleksitas kegiatan usaha Bank. | E48: 2 | F48: Tim IT secara rutin melakukan pemantauan dan evaluasi. Disamping itu, pembenahan tetap dilakukan secara rutin melalui rencana bisnis bank setiap tahunnya dalam rangka peningkatan ketahanan sistem dan keamanan siber | H48: DTI
D49: 3.3.d. Sebagai bagian dari sistem informasi manajemen risiko terkait keamanan siber, laporan tingkat maturitas keamanan siber disusun secara berkala oleh unit atau fungsi yang bertugas menangani ketahanan dan keamanan siber Bank. Frekuensi penyampaian laporan tingkat maturitas keamanan siber kepada Direksi terkait dan komite manajemen risiko harus ditingkatkan sesuai kebutuhan terutama dalam hal terdapat perkembangan serangan dan ancaman siber yang berubah dengan cepat. | E49: 2 | F49: Laporan tingkat maturitas keamanan siber disusun secara berkala | H49: DMR
D50: 3.3.e. Bank memastikan sistem informasi manajemen risiko terkait keamanan siber mendukung pelaksanaan pelaporan tingkat maturitas keamanan siber kepada Otoritas Jasa Keuangan. | E50: 2 | F50: Tools security yang dimiliki dinilai dapat mendukung pelaksanaan pelaporan tingkat maturitas keamanan siber | H50: DTI
A51: 4 | B51: Sistem Pengendalian Risiko terkait Keamanan Siber | C51: 4.1. Kecukupan Sistem Pengendalian Intern | D51: 4.1.a. Bank melaksanakan sistem pengendalian intern secara efektif dalam penerapan manajemen risiko terkait keamanan siber dengan mengacu pada kebijakan dan prosedur yang telah ditetapkan | E51: 3 | F51: Sudah melaksanakan pemeriksaan berdasarkan ketentuan baik internal maupun eksternal | H51: DPg
D52: 4.1.b. Bank melaksanakan sistem pengendalian intern secara efektif dalam penerapan proses ketahanan siber dengan mengacu pada kebijakan dan prosedur yang telah ditetapkan. | E52: 2 | F52: Sudah melaksanakan pemeriksaan berdasarkan ketentuan baik internal maupun eksternal | H52: DPg
D53: 4.1.c. Satuan kerja audit intern melakukan pemantauan terhadap perbaikan hasil temuan. Temuan yang belum ditindaklanjuti harus dilaporkan kepada Direksi dan/atau Dewan Komisaris untuk diambil langkah yang diperlukan. | E53: 2 | F53: Seluruh temuan dilaporkan kepada Direksi/Komisaris | H53: DPg
D54: 4.1.d. Bank memiliki sistem rotasi rutin untuk menghindari potensi self-dealing, persekongkolan atau penyembunyian suatu dokumentasi atau aktivitas yang tidak wajar. | E54: 1 | F54: Bank sudah menerapkan sistem rotasi/mutasi pada seluruh unit kerja | H54: DSDM
C55: 4.2. Kecukupan Kaji Ulang | D55: 4.2.a. Bank melakukan kaji ulang dan evaluasi terhadap penerapan manajemen risiko terkait keamanan siber secara berkala sesuai dengan karakteristik dan kompleksitas Bank | E55: 2 | F55: Divisi Manajemen Risiko menerbitkan ketentuan mengenai katahanan dan keamanan siber | H55: DPg, DMR
D56: 4.2.b. Bank memastikan satuan kerja yang menjalankan fungsi manajemen risiko terkait keamanan siber melakukan kaji ulang dan evaluasi secara memadai. | E56: 2 | F56: Menjadi objek pemantauan dan pemeriksaan | H56: DPg, DMR
D57: 4.2.c. Bank memastikan satuan kerja audit intern melakukan kaji ulang dan evaluasi secara memadai. | E57: 2 | F57: Menjadi objek pemantauan dan pemeriksaan | H57: DPg
D58: 4.2.d. Bank memastikan pihak yang melakukan kaji ulang dan evaluasi atas penerapan manajemen risiko terkait keamanan siber memiliki independensi dan kompetensi yang baik serta metode kaji ulang yang andal. | E58: 2 | F58: Menjadi objek pemantauan dan pemeriksaan | H58: DPg, DMR
D59: 4.2.e. Bank memastikan bahwa hasil kaji ulang dan evaluasi atas penerapan manajemen risiko terkait keamanan siber telah disampaikan kepada Direksi dan Dewan Komisaris untuk diambil langkah perbaikan dan/atau penyempurnaan manajemen risiko terkait keamanan siber | E59: 2 | F59: Seluruh temuan terkait siber akan dilaporkan kepada Direksi/Komisaris. Hasil kaji ulang disampaikan ke Direksi | H59: DPg, DMR
D61: Avg | E61: =SUM(E4:E59)/56 -> 2.0178571
D62: Peringkat | E62: =IF(E61<=1,("Strong"),IF(E61<=2,("Satisfactory"),IF(E61<=3,("Fair"),IF(E61<=4,("Marginal"),"Unsatisfactory")))) -> Fair
D66: KETERANGAN PENERAPAN KONTROL
D67: Sangat Memadai | E67: 1
D68: Memadai | E68: 2
D69: Cukup Memadai | E69: 3
D70: Belum Memadai | E70: 4
D71: Belum Diterapkan | E71: 5

Sheet Kualitas Ketahanan
A1: F. Kertas Kerja Penilaian Kualitas Penerapan Proses Ketahanan Siber
A3: No | B3: Domain | C3: Kontrol | D3: Penerapan Kontrol | E3: Penjelasan | F3: Referensi Dokumen | G3: Departemen/Unit/Jabatan yang Bertanggung Jawab
A4: 1 | B4: Proses Identifikasi Aset, Ancaman, dan Kerentanan | C4: 1.a. Bank menerapkan manajemen aset melalui inventarisasi dan penilaian aset TI (antara lain perangkat keras, perangkat lunak, jaringan, dan infrastruktur) serta pencatatan konfigurasi secara efektif. | D4: 2 | E4: Aset teknologi informasi telah diinventarisir dan telah dinilai | F4: SK Kebijakan Sistem Manajemen Keamanan Informasi | G4: DTI
C5: 1.b. Bank melakukan identifikasi kerentanan dan pemantauan terhadap perkembangan siber terkini untuk mengidentifikasi ancaman siber. | D5: 2 | E5: Bank telah mengimplementasikan SOC yang didalamnya sudah termasuk threat intelligence, melakukan vulnerability assessment dan penetration test | G5: DTI, DMR
C6: 1.c. Bank melakukan pengujian keamanan siber secara berkala. | D6: 2 | E6: Bank telah melakukan vulnerability assessment dengan melaksanakan penetration test secara berkala. Disamping itu, Bank juga melakukan uji keamanan berdasarkan skenario table top dan cyber range exercise pada pelaksanaan live operasional DRC | G6: DTI, DMR
A7: 2 | B7: Proses Pelindungan Aset | C7: 2.a. Bank menerapkan pengendalian keamanan (security control) yang komprehensif sesuai dengan hasil identifikasi aset, ancaman, dan kerentanan. | D7: 2 | E7: Tools security sebagai perimeter security standar yang sudah diimplementasikan adalah firewall, web application firewall, endpoint security, antispam. Penguatan lainnya adalah Bank melakukan pengujian kehandalan dan keamanan dengan melakukan penetration test terhadap aplikasi-aplikasi critical | G7: DTI, DMR, DUM
C8: 2.b. Bank melakukan pemeliharaan dan perbaikan terhadap pengendalian keamanan atas aset TI sesuai dengan kebijakan dan prosedur yang berlaku. | D8: 2 | E8: Secara rutin dilakukan pemantauan secara manual, pemantauan dengan layanan SOC. Bank juga melakukan update knowledge base tools security secara rutin seperti update firmware, definition, patching, serta secara rutin dan otomatis melakukan update IP yang berstatus bad reputation ataupun IP yang melakukan jenis atau pola serangan siber | G8: DTI
C9: 2.c. Bank menerapkan sistem pengamanan yang dikelola dengan baik sesuai kebijakan dan prosedur yang berlaku. | D9: 2 | E9: Tools security sebagai perimeter security standar yang sudah diimplementasikan adalah firewall, web application firewall, endpoint security, antispam. Penguatan lainnya adalah Bank melakukan pengujian kehandalan dan keamanan dengan melakukan penetration test terhadap aplikasi-aplikasi critical | G9: DTI
C10: 2.d. Bank melakukan penginian pengendalian keamanannya secara berkala untuk memastikan kecukupan kontrol keamanan yang digunakan sesuai dengan hasil terkini dari proses identifikasi | D10: 1 | E10: Bank secara rutin melakukan update terhadap IP Bad Reputation, patching firmware firewall dan update endpoint security | G10: DTI
C11: 2.e. Bank menerapkan manajemen keamanan data dan informasi serta memastikan bahwa data dan/atau informasi dikelola sesuai dengan strategi manajemen risiko terkait keamanan siber pada organisasi untuk melindungi kerahasiaan, integritas, serta ketersediaan data dan informasi | D11: 2 | E11: Bank telah menerapkan manajemen keamanan data dan informasi seperti mengimplementasikan infrastruktur keamanan, penggunaan protocol yang secure, hak akses control pada aplikasi, penggunaan secure network, penerapan two factor authentication | G11: DTI
C12: 2.f. Bank menerapkan manajemen pelindungan terhadap jaringan, perangkat keras, dan perangkat lunak. | D12: 2 | E12: Perlindungan terhadap jaringan dilakukan dengan mengimplementasikan SOC, firewall, web application firewall | G12: DTI
C13: 2.g. Bank menerapkan manajemen pelindungan terhadap akses dan pengguna untuk mencegah tindakan tidak terotorisasi pada perangkat, infrastruktur jaringan, dan komponen sistem yang dikelola oleh Bank. | D13: 2 | E13: Perlindungan terhadap akses dan penggunaan untuk mencegah tindakan terotorisasi dilakukan pada layer aplikasi berdasarkan user matriks access control | G13: DTI
C14: 2.h. Bank menerapkan pelindungan yang memadai dalam pelaksanaan kerja sama antara Bank dengan pihak penyedia jasa TI, termasuk dalam penggunaan cloud. | D14: 1 | E14: Bank melakukan verifikasi terhadap perusahaan yang bekerjsaman dengan Bank dan membuat klausa perlindungan data pada perjanjian kerja sama | G14: DTI
C15: 2.i. Bank memastikan penerapan secure coding dalam pengembangan sistem dan aplikasi untuk meminimalisasi kerentanan atas sistem dan aplikasi. | D15: 2 | E15: Bank menerapkan proses SDLC yang memadai | G15: DTI
C16: 2.j. Bank memastikan pelaksanaan patching berjalan dengan baik serta memastikan keandalan dan kemutakhiran seluruh komponen perangkat lunak, jaringan komunikasi, database, dan sistem operasi (operating system) Bank. | D16: 3 | E16: Patching belum dilakukan secara maksimal | G16: DTI
A17: 3 | B17: Proses Deteksi Insiden Siber | C17: 3.a. Bank memastikan ketersediaan dokumentasi kinerja dasar (baseline performance) atas fungsi kritis Bank dan sistem pendukung, agar setiap penyimpangan dapat dideteksi secara tepat waktu serta aktivitas dan kejadian anomali dapat ditandai untuk ditindaklanjuti. | D17: 2 | E17: Log atas aktifitas security pada layanan-layanan critical seperti server, firewall, waf, router, core switch telah diintegrasikan dengan log collector yang merupakan satu kesatuan layanan SOC. Layanan SOC juga memiliki dashboard yang dapat diakses secara jaringan dengan kondisi yang realtime | G17: DTI
C18: 3.b. Bank melakukan pemantauan atas aktivitas mencurigakan serta melakukan pengelolaan dan pengujian terhadap proses dan prosedur deteksi untuk memastikan aktivitas anomali dapat dideteksi secara tepat waktu. | D18: 2 | E18: Tools yang digunakan untuk monitoring dan deteksi adalah firewall (next generation firewall), web application firewall, antivirus, antispam. Disamping itu, Bank juga telah mengimplementasikan layanan SOC sebagai bagian tools security untuk monitoring dan mendeteksi serangan siber. Pada layanan SOC juga sudah dibekali dengan threat intelligence | G18: DTI
C19: 3.c. Bank melakukan pemantauan atau deteksi secara berkelanjutan terhadap kerentanan untuk memastikan efektivitas upaya pelindungan yang telah diterapkan. | D19: 2 | E19: Tools yang digunakan untuk monitoring dan deteksi adalah firewall (next generation firewall), web application firewall, antivirus, antispam. Disamping itu, Bank juga telah mengimplementasikan layanan SOC sebagai bagian tools security untuk monitoring dan mendeteksi serangan siber. Pada layanan SOC juga sudah dibekali dengan threat intelligence | G19: DTI
C20: 3.d. Bank memastikan ketersediaan proses untuk mendeteksi insiden siber secara memadai. | D20: 2 | E20: Bank telah mengimplementasikan Firewall, Web Application Firewall, SOC, Antispam, Endpoint Security, Access List dan network VPN | G20: DTI, DMR
C21: 3.e. Bank melakukan analisis terhadap ancaman dan kerentanan dari suatu insiden siber untuk memastikan penanganan insiden secara efektif sehingga dapat mencegah terjadinya gangguan pada layanan dan/atau operasional Bank. | D21: 2 | E21: Bank melakukan analisis terhadap ancamanan dan kerentanan yang terjadi | G21: DTI, DMR
A22: 4 | B22: Proses Penanggulangan dan Pemulihan Insiden Siber | C22: 4.a. Bank menetapkan rencana penanggulangan dan pemulihan insiden siber untuk memastikan penanggulangan dan pengembalian layanan yang tepat waktu sesuai dengan risiko yang ditimbulkan, dengan dampak minimal. | D22: 2 | E22: Bank telah melakukan simulasi ketahanan siber yang dilakukan secara bersamaan dengan pelaksanaan live operasional DRC | G22: DTI, DMR
C23: 4.b. Bank menetapkan peran serta tugas dan tanggung jawab tim tanggap insiden siber untuk memastikan penanggulangan dan pemulihan insiden siber dilaksanakan dengan dampak minimal terhadap layanan dan operasional Bank. | D23: 1 | E23: Bank telah membentuk tim Keamanan Sistem Informasi, bank sudah membentuk Tim Tanggap Insiden Siber | F23: SK No. 214 /Dir/DMR-MROL/SK/2024 tanggal 21 Oktober 2024 tentang Tim Tanggap Insiden Siber PT Bank Sumut | G23: DTI, DMR
C24: 4.c. Bank menerapkan prosedur pemulihan dan upaya untuk mencegah penyebaran dampak dari suatu insiden siber dengan memitigasi dampak dan menanggulangi insiden siber tersebut. | D24: 2 | E24: Bank telah memiliki ketentuan yang mengatur insiden siber | G24: DTI, DMR
C25: 4.d. Bank melakukan analisis untuk memastikan langkah penanggulangan dan pemulihan insiden siber dijalankan dengan tepat. | D25: 2 | E25: Bank senantiasa melakukan analisis terhadap insiden-insiden yang terjadi | G25: DTI, DMR
C26: 4.e. Bank melakukan eskalasi dan pelaporan atas insiden siber sesuai dengan jalur komunikasi yang telah ditetapkan | D26: 2 | E26: Bank telah memiliki prosedur pelaporan atas insiden siber | G26: DTI, DMR
C27: 4.f. Bank melakukan analisis pasca insiden sebagai bahan pelajaran terpetik (lesson learned) dalam penanggulangan dan pemulihan insiden siber untuk perbaikan berkelanjutan | D27: 2 | E27: Bank senantiasa melakukan analisis pasca insiden serta menjadikan bahan pembelajaran untuk diimplementasikan | G27: DTI, DMR
C29: Avg | D29: =SUM(D4:D27)/24 -> 1.9166667
C30: Peringkat | D30: =IF(D29<=1,("Strong"),IF(D29<=2,("Satisfactory"),IF(D29<=3,("Fair"),IF(D29<=4,("Marginal"),"Unsatisfactory")))) -> Satisfactory
C34: KETERANGAN PENERAPAN KONTROL
C35: Sangat Memadai | D35: 1
C36: Memadai | D36: 2
C37: Cukup Memadai | D37: 3
C38: Belum Memadai | D38: 4
C39: Belum Diterapkan | D39: 5

Sheet Maturitas
C3: Peringkat Maturitas Kemanan Siber
C5: Inherent Risk Rating | E5: Nilai Rating | F5: Kualifikasi Rating | H5: SKALA RATING INHERENT
C6: 1 | D6: Kualitas Penerapan Manajemen Risiko terkait Keamanan Siber | E6: =KPMR!E61 -> 2.0178571 | F6: =KPMR!E62 -> Fair | H6: - Tingkat 1 | I6: 1 < nilai < 2
H7: - Tingkat 2 | I7: 2 < nilai < 3
C8: 2 | D8: Kualitas Penerapan Proses Ketahanan Siber | E8: ='Kualitas Ketahanan'!D29 -> 1.9166667 | F8: ='Kualitas Ketahanan'!D30 -> Satisfactory | H8: - Tingkat 3 | I8: 3 < nilai < 4
H9: - Tingkat 4 | I9: 4 < nilai < 5
E10: =(E6+E8)/2 -> 1.9672619 | F10: =IF(E10<=1,("Tingkat 1"),IF(E10<=2,("Tingkat 2"),IF(E10<=3,("Tingkat 3"),IF(E10<=4,("Tingkat 4"),"Tingkat 5")))) -> Tingkat 2 | H10: - Tingkat 5 | I10: nilai > 5

Sheet Matriks KPMR
A1: Matriks Penetapan Kualitas Penerapan Manajemen Risiko terkait Keamanan Siber
A3: Peringkat | B3: Defenisi Peringkat
A4: STRONG (1) | B4: Kualitas penerapan manajemen risiko terkait keamanan siber sangat memadai. Meskipun terdapat kelemahan minor tetapi kelemahan tersebut tidak signifikan sehingga dapat diabaikan. Contoh karakteristik Bank yang termasuk dalam peringkat Strong (1): a. pengawasan aktif oleh Direksi dan Dewan Komisaris secara keseluruhan sangat memadai; b. SDM sangat memadai, baik dari sisi kuantitas maupun kompetensi pada fungsi manajemen risiko terkait keamanan siber; c. struktur organisasi terkait penerapan manajemen risiko terkait keamanan siber pada seluruh satuan kerja telah berjalan dengan sangat baik; d. Direksi dan Dewan Komisaris memiliki kesadaran (awareness) dan pemahaman mengenai manajemen risiko terkait keamanan siber yang sangat baik; e. budaya dan kesadaran manajemen risiko terkait keamanan siber telah dikembangkan dan diimplementasikan dengan sangat baik di seluruh lingkungan organisasi Bank; f. program peningkatan kapasitas SDM di bidang keamanan informasi dan manajemen risiko terkait keamanan siber sangat memadai; g. penetapan tingkat risiko yang akan diambil (risk appetite) dan toleransi risiko (risk tolerance) sangat memadai serta sangat sesuai dengan sasaran strategis dan strategi bisnis Bank; h. strategi manajemen risiko terkait keamanan siber sangat sejalan dengan tingkat risiko yang akan diambil (risk appetite) dan toleransi risiko (risk tolerance) terkait keamanan siber; i. kebijakan dan prosedur manajemen risiko serta penetapan limit risiko terkait keamanan siber sangat memadai dan tersedia untuk seluruh area manajemen risiko terkait keamanan siber, sejalan dengan penerapan, dan dipahami dengan baik oleh pegawai; j. proses manajemen risiko terkait keamanan siber sangat memadai dalam mengidentifikasi, mengukur, memantau, dan mengendalikan risiko terkait keamanan siber; k. sistem informasi manajemen risiko terkait keamanan siber sangat baik sehingga menghasilkan laporan risiko terkait keamanan siber yang komprehensif dan terintegrasi kepada Direksi dan Dewan Komisaris; l. sistem pengendalian intern sangat efektif dalam mendukung pelaksanaan manajemen risiko terkait keamanan siber; m. pelaksanaan kaji ulang independen oleh satuan kerja audit intern dan satuan kerja yang menjalankan fungsi manajemen risiko terkait keamanan siber sangat memadai, baik dari sisi metodologi, frekuensi, maupun pelaporan kepada Direksi dan Dewan Komisaris; n. secara umum tidak terdapat kelemahan yang signifikan berdasarkan hasil kaji ulang independen; o. tindak lanjut atas kaji ulang independen telah dilaksanakan dengan sangat memadai.
A5: SATISFACTORY (2) | B5: Kualitas penerapan manajemen risiko terkait keamanan siber memadai. Meskipun terdapat beberapa kelemahan minor, kelemahan tersebut dapat diselesaikan pada aktivitas bisnis normal. Contoh karakteristik Bank yang termasuk dalam peringkat Satisfactory (2): a. pengawasan aktif oleh Direksi dan Dewan Komisaris secara keseluruhan memadai; b. SDM memadai, baik dari sisi kuantitas maupun kompetensi pada fungsi manajemen risiko terkait keamanan siber; c. struktur organisasi terkait penerapan manajemen risiko terkait keamanan siber pada seluruh satuan kerja telah berjalan dengan baik; d. Direksi dan Dewan Komisaris memiliki kesadaran (awareness) dan pemahaman mengenai manajemen risiko terkait keamanan siber yang baik; e. budaya dan kesadaran manajemen risiko terkait keamanan siber telah dikembangkan dan diimplementasikan dengan baik di seluruh lingkungan organisasi Bank; f. program peningkatan kapasitas SDM di bidang keamanan informasi dan manajemen risiko terkait keamanan siber memadai; g. penetapan tingkat risiko yang akan diambil (risk appetite) dan toleransi risiko (risk tolerance) memadai serta sesuai dengan sasaran strategis dan strategi bisnis Bank; h. strategi manajemen risiko terkait keamanan siber sejalan dengan tingkat risiko yang akan diambil (risk appetite) dan toleransi risiko (risk tolerance) terkait keamanan siber; i. kebijakan dan prosedur manajemen risiko serta penetapan limit risiko terkait keamanan siber memadai dan tersedia untuk seluruh area manajemen risiko terkait keamanan siber, sejalan dengan penerapan, dan dipahami dengan baik oleh pegawai meskipun terdapat kelemahan minor; j. proses manajemen risiko terkait keamanan siber memadai; o. tindak lanjut atas kaji ulang independen telah dilaksanakan dengan memadai dalam mengidentifikasi, mengukur, memantau, dan mengendalikan risiko terkait keamanan siber; k. sistem informasi manajemen risiko terkait keamanan siber baik sehingga menghasilkan laporan risiko terkait keamanan siber yang komprehensif dan terintegrasi kepada Direksi dan Dewan Komisaris; l. sistem pengendalian intern efektif dalam mendukung pelaksanaan manajemen risiko terkait keamanan siber; m. pelaksanaan kaji ulang independen oleh satuan kerja audit intern dan satuan kerja yang menjalankan fungsi manajemen risiko terkait keamanan siber memadai, baik dari sisi metodologi, frekuensi, maupun pelaporan kepada Direksi dan Dewan Komisaris; n. terdapat kelemahan yang tidak signifikan berdasarkan hasil kaji ulang independen; o. tindak lanjut atas kaji ulang independen telah dilaksanakan dengan memadai.
A6: FAIR (3) | B6: Kualitas penerapan manajemen risiko terkait keamanan siber cukup memadai. Meskipun persyaratan minimum terpenuhi, terdapat beberapa kelemahan yang membutuhkan perhatian manajemen. Contoh karakteristik Bank yang termasuk dalam peringkat Fair (3): a. pengawasan aktif oleh Direksi dan Dewan Komisaris secara keseluruhan cukup memadai; b. SDM cukup memadai, baik dari sisi kuantitas maupun kompetensi pada fungsi manajemen risiko terkait keamanan siber; c. struktur organisasi terkait penerapan manajemen risiko terkait keamanan siber pada seluruh satuan kerja telah berjalan dengan cukup baik; d. Direksi dan Dewan Komisaris memiliki kesadaran (awareness) dan pemahaman mengenai manajemen risiko terkait keamanan siber yang cukup baik; e. budaya dan kesadaran manajemen risiko terkait keamanan siber telah dikembangkan dan diimplementasikan dengan cukup baik di seluruh lingkungan organisasi Bank; f. program peningkatan kapasitas SDM di bidang keamanan informasi dan manajemen risiko terkait keamanan siber cukup memadai; g. penetapan tingkat risiko yang akan diambil (risk appetite) dan toleransi risiko (risk tolerance) cukup memadai namun tidak selalu sesuai dengan sasaran strategis dan strategi bisnis Bank; h. strategi manajemen risiko terkait keamanan siber cukup sejalan dengan tingkat risiko yang akan diambil (risk appetite) dan toleransi risiko (risk tolerance) terkait keamanan siber; i. kebijakan dan prosedur manajemen risiko serta penetapan limit risiko terkait keamanan siber cukup memadai namun tidak selalu sejalan dengan penerapan; j. proses manajemen risiko terkait keamanan siber cukup memadai dalam mengidentifikasi, mengukur, memantau, dan mengendalikan risiko terkait keamanan siber; k. sistem informasi manajemen risiko terkait keamanan siber cukup baik, termasuk pelaporan risiko terkait keamanan siber yang komprehensif dan terintegrasi kepada Direksi dan Dewan Komisaris; l. sistem pengendalian intern cukup efektif dalam mendukung pelaksanaan manajemen risiko terkait keamanan siber; m. pelaksanaan kaji ulang independen oleh satuan kerja audit intern dan satuan kerja yang menjalankan fungsi manajemen risiko terkait keamanan siber cukup memadai, baik dari sisi metodologi, frekuensi, maupun pelaporan kepada Direksi dan Dewan Komisaris; n. terdapat kelemahan yang cukup signifikan berdasarkan hasil kaji ulang independen yang memerlukan perhatian manajemen; o. tindak lanjut atas kaji ulang independen telah dilaksanakan dengan cukup memadai.
A7: MARGINAL (4) | B7: Kualitas penerapan manajemen risiko terkait keamanan siber kurang memadai. Terdapat kelemahan signifikan pada berbagai aspek manajemen risiko terkait keamanan siber yang memerlukan tindakan korektif segera. Contoh karakteristik Bank yang termasuk dalam peringkat Marginal (4): a. pengawasan aktif oleh Direksi dan Dewan Komisaris secara keseluruhan kurang memadai, dan terdapat kelemahan pada berbagai aspek penilaian yang memerlukan perbaikan segera; b. SDM kurang memadai, baik dari sisi kuantitas maupun kompetensi pada fungsi manajemen risiko terkait keamanan siber; c. struktur organisasi terkait penerapan manajemen risiko terkait keamanan siber pada seluruh satuan kerja kurang berjalan dengan baik; d. kelemahan signifikan atas kesadaran (awareness) dan pemahaman Direksi dan Dewan Komisaris mengenai manajemen risiko terkait keamanan siber; e. budaya dan kesadaran manajemen risiko terkait keamanan siber kurang dikembangkan dan diimplementasikan dengan baik di seluruh lingkungan organisasi Bank; f. program peningkatan kapasitas SDM di bidang keamanan informasi dan manajemen risiko terkait keamanan siber kurang memadai; g. penetapan tingkat risiko yang akan diambil (risk appetite) dan toleransi risiko (risk tolerance) kurang memadai serta tidak sesuai dengan sasaran strategis dan strategi bisnis Bank; h. strategi manajemen risiko terkait keamanan siber kurang sejalan dengan tingkat risiko yang akan diambil (risk appetite) dan toleransi risiko (risk tolerance) terkait keamanan siber; i. kebijakan dan prosedur manajemen risiko serta penetapan limit risiko terkait keamanan siber kurang memadai dan tidak sejalan dengan penerapan; j. proses manajemen risiko terkait keamanan siber kurang memadai dalam mengidentifikasi, mengukur, memantau, dan mengendalikan risiko terkait keamanan siber; k. kelemahan signifikan pada sistem informasi manajemen risiko terkait keamanan siber, termasuk pelaporan risiko terkait keamanan siber kepada Direksi dan Dewan Komisaris, yang memerlukan perbaikan segera; l. sistem pengendalian intern kurang efektif dalam mendukung pelaksanaan manajemen risiko terkait keamanan siber; m. pelaksanaan kaji ulang independen oleh satuan kerja audit intern dan satuan kerja yang menjalankan fungsi manajemen risiko terkait keamanan siber kurang memadai, baik dari sisi metodologi, frekuensi, maupun pelaporan kepada Direksi dan Dewan Komisaris; n. terdapat kelemahan yang signifikan berdasarkan hasil kaji ulang independen yang memerlukan perbaikan segera; o. tindak lanjut atas kaji ulang independen dilaksanakan dengan kurang memadai.
A8: UNSATISFACTORY (5) | B8: Kualitas penerapan manajemen risiko terkait keamanan siber tidak memadai. Terdapat kelemahan signifikan pada berbagai aspek manajemen risiko terkait keamanan siber yang tindakan penyelesaiannya di luar kemampuan manajemen. Contoh karakteristik Bank yang termasuk dalam peringkat Unsatisfactory (5): a. pengawasan aktif oleh Direksi dan Dewan Komisaris secara keseluruhan tidak memadai serta terdapat kelemahan pada hampir seluruh aspek penilaian dan tindakan penyelesaiannya di luar kemampuan Bank; b. SDM tidak memadai, baik dari sisi kuantitas maupun kompetensi pada fungsi manajemen risiko terkait keamanan siber; c. struktur organisasi terkait penerapan manajemen risiko terkait keamanan siber pada seluruh satuan kerja tidak berjalan dengan baik; d. kesadaran (awareness) dan pemahaman Direksi dan Dewan Komisaris mengenai manajemen risiko terkait keamanan siber sangat lemah; e. budaya dan kesadaran manajemen risiko terkait keamanan siber tidak dikembangkan dan diimplementasikan di lingkungan organisasi Bank atau belum ada sama sekali; f. program peningkatan kapasitas SDM di bidang keamanan informasi dan manajemen risiko terkait keamanan siber tidak memadai; g. penetapan tingkat risiko yang akan diambil (risk appetite) dan toleransi risiko (risk tolerance) tidak memadai serta tidak terdapat kaitan dengan sasaran strategis dan strategi bisnis Bank; h. strategi manajemen risiko terkait keamanan siber tidak sejalan dengan tingkat risiko yang akan diambil (risk appetite) dan toleransi risiko (risk tolerance) terkait keamanan siber; i. kelemahan sangat signifikan pada kebijakan dan prosedur manajemen risiko serta penetapan limit risiko terkait keamanan siber; j. proses manajemen risiko terkait keamanan siber tidak memadai dalam mengidentifikasi, mengukur, memantau, dan mengendalikan risiko terkait keamanan siber; k. kelemahan fundamental pada sistem informasi manajemen risiko terkait keamanan siber; l. sistem pengendalian intern tidak efektif dalam mendukung pelaksanaan manajemen risiko terkait keamanan siber; m. pelaksanaan kaji ulang independen oleh satuan kerja audit intern dan satuan kerja yang menjalankan fungsi manajemen risiko terkait keamanan siber tidak memadai, serta terdapat kelemahan pada metodologi, frekuensi, dan/atau pelaporan kepada Direksi dan Dewan Komisaris yang memerlukan perbaikan fundamental; n. terdapat kelemahan yang sangat signifikan berdasarkan hasil kaji ulang independen yang memerlukan perbaikan segera; o. tindak lanjut atas kaji ulang independen tidak memadai atau tidak ada.

Sheet Matriks Ketahanan
A1: Matriks Penetapan Kualitas Penerapan Manajemen Risiko terkait Keamanan Siber
A3: Peringkat | B3: Defenisi Peringkat
A4: STRONG (1) | B4: Kualitas penerapan proses ketahanan siber sangat memadai. Meskipun terdapat kelemahan minor tetapi kelemahan tersebut tidak signifikan sehingga dapat diabaikan. Contoh karakteristik Bank yang termasuk dalam peringkat Strong (1): a. proses identifikasi aset, ancaman dan kerentanan sangat memadai; b. proses pelindungan aset dilaksanakan dengan sangat baik; c. proses deteksi insiden siber sangat andal dan teruji; d. proses penanggulangan dan pemulihan insiden siber dilaksanakan dengan sangat baik dan tidak menimbulkan gangguan yang signifikan.
A5: SATISFACTORY (2) | B5: Kualitas penerapan proses ketahanan siber memadai. Meskipun terdapat beberapa kelemahan minor, kelemahan tersebut dapat diselesaikan pada aktivitas bisnis normal. Contoh karakteristik Bank yang termasuk dalam peringkat Satisfactory (2): a. proses identifikasi aset, ancaman, dan kerentanan memadai; b. proses pelindungan aset dilaksanakan dengan baik; c. proses deteksi insiden siber andal dan teruji; d. proses penanggulangan dan pemulihan insiden siber dilaksanakan dengan baik meskipun terdapat gangguan namun tidak bersifat signifikan.
A6: FAIR (3) | B6: Kualitas penerapan proses ketahanan siber cukup memadai. Meskipun persyaratan minimum terpenuhi, terdapat beberapa kelemahan yang membutuhkan perhatian manajemen. Contoh karakteristik Bank yang termasuk dalam peringkat Fair (3): a. proses identifikasi aset, ancaman, dan kerentanan cukup memadai; b. proses pelindungan aset dilaksanakan dengan cukup baik; c. proses deteksi insiden siber cukup andal dan teruji; d. proses penanggulangan dan pemulihan insiden siber dilaksanakan dengan cukup baik namun tetap menimbulkan gangguan yang bersifat minor.
A7: MARGINAL (4) | B7: Kualitas penerapan proses ketahanan siber kurang memadai. Terdapat kelemahan signifikan pada berbagai proses untuk menjaga ketahanan siber yang memerlukan tindakan korektif segera. Contoh karakteristik Bank yang termasuk dalam peringkat Marginal (4): a. proses identifikasi aset, ancaman, dan kerentanan kurang memadai; b. proses pelindungan aset dilaksanakan dengan kurang baik; c. proses deteksi insiden siber kurang andal dan teruji; d. proses penanggulangan dan pemulihan insiden siber dilaksanakan dengan kurang baik dan menimbulkan gangguan yang signifikan.
A8: UNSATISFACTORY (5) | B8: Kualitas penerapan proses ketahanan siber tidak memadai. Terdapat kelemahan signifikan pada berbagai proses untuk menjaga ketahanan siber yang tindakan penyelesaiannya di luar kemampuan manajemen. Contoh karakteristik Bank yang termasuk dalam peringkat Unsatisfactory (5): a. proses identifikasi aset, ancaman, dan kerentanan tidak memadai; b. proses pelindungan aset tidak dilaksanakan dengan baik; c. proses deteksi insiden siber tidak andal dan teruji; d. proses penanggulangan dan pemulihan insiden siber tidak dilaksanakan dengan baik sehingga menimbulkan gangguan yang sangat signifikan.

Sheet Matriks Maturitas
A1: Matriks Penetapan Tingkat Maturitas Keamanan Siber
A3: Peringkat | B3: Defenisi Peringkat
A4: TINGKAT 1 | B4: Mencerminkan kondisi maturitas keamanan siber Bank yang secara umum sangat tinggi, tercermin dari penerapan manajemen risiko terkait keamanan siber dan penerapan proses ketahanan siber yang secara umum sangat baik. Dalam hal terdapat kelemahan maka secara umum kelemahan tersebut tidak signifikan.
A5: TINGKAT 2 | B5: Mencerminkan kondisi maturitas keamanan siber Bank yang secara umum tinggi, tercermin dari penerapan manajemen risiko terkait keamanan siber dan penerapan proses ketahanan siber yang secara umum baik. Dalam hal terdapat kelemahan maka secara umum kelemahan tersebut kurang signifikan.
A6: TINGKAT 3 | B6: Mencerminkan kondisi maturitas keamanan siber Bank yang secara umum cukup, tercermin dari penerapan manajemen risiko terkait keamanan siber dan penerapan proses ketahanan siber yang secara umum cukup baik. Dalam hal terdapat kelemahan maka secara umum kelemahan tersebut cukup signifikan dan apabila tidak berhasil diatasi dengan baik oleh manajemen dapat mengganggu kelangsungan usaha Bank.
A7: TINGKAT 4 | B7: Mencerminkan kondisi maturitas keamanan siber Bank yang secara umum rendah, tercermin dari penerapan manajemen risiko terkait keamanan siber dan penerapan proses ketahanan siber yang secara umum kurang baik. Terdapat kelemahan yang secara umum signifikan dan tidak dapat diatasi dengan baik oleh manajemen serta mengganggu kelangsungan usaha Bank.
A8: TINGKAT 5 | B8: Mencerminkan kondisi maturitas keamanan siber Bank yang secara umum sangat rendah, tercermin dari penerapan manajemen risiko terkait keamanan siber dan penerapan proses ketahanan siber yang secara umum kurang baik. Terdapat kelemahan yang secara umum sangat signifikan sehingga untuk mengatasinya diperlukan dukungan dana dari pemegang saham atau sumber dana dari pihak lain untuk memperkuat penerapan manajemen risiko terkait keamanan siber dan penerapan proses ketahanan siber pada Bank.

Sheet RATING SIBER
C3: Peringkat Tingkat Risiko Keamanan Siber
C5: Inherent Risk Rating | E5: Nilai Rating | F5: Kualifikasi Rating | H5: SKALA RATING INHERENT
C6: 1 | D6: Peringkat Risiko Inheren terkait Keamanan Siber | E6: ='All Inheren'!E10 -> 1.9583333 | F6: ='All Inheren'!F10 -> Low to Moderate | H6: - LOW | I6: 1 < nilai < 2
H7: - LOW TO MODERATE | I7: 2 < nilai < 3
C8: 2 | D8: Peringkat Tingkat Maturitas Keamanan Siber | E8: =Maturitas!E10 -> 1.9672619 | F8: =Maturitas!F10 -> Tingkat 2 | H8: - MODERATE | I8: 3 < nilai < 4
H9: - MODERATE TO HIGH | I9: 4 < nilai < 5
E10: =(E6+E8)/2 -> 1.9627976 | F10: =IF(E10<=1,("Low"),IF(E10<=2,("Low to Moderate"),IF(E10<=3,("Moderate"),IF(E10<=4,("Moderate to High"),"High")))) -> Low to Moderate | H10: - HIGH | I10: nilai > 5
